{"info": {}, "categories": {"label": {"labels": [{"name": "SORXX", "parent": "", "attributes": []}, {"name": "differentPlant", "parent": "", "attributes": []}], "attributes": ["occluded"]}}, "items": [{"id": "SORXX/125830/SORKM_125830_2021Y10M28D_15H27M22S_img", "annotations": [], "attr": {"frame": 0}}, {"id": "SORXX/125830/SORKM_125830_2021Y10M28D_17H19M09S_img", "annotations": [], "attr": {"frame": 1}}, {"id": "SORXX/125830/SORKM_125830_2021Y10M29D_01H00M58S_img", "annotations": [], "attr": {"frame": 2}}, {"id": "SORXX/125830/SORKM_125830_2021Y10M29D_08H45M31S_img", "annotations": [], "attr": {"frame": 3}}, {"id": "SORXX/125830/SORKM_125830_2021Y10M29D_12H45M08S_img", "annotations": [], "attr": {"frame": 4}}, {"id": "SORXX/125830/SORKM_125830_2021Y10M30D_01H44M08S_img", "annotations": [], "attr": {"frame": 5}}, {"id": "SORXX/125830/SORKM_125830_2021Y10M30D_12H18M27S_img", "annotations": [], "attr": {"frame": 6}}, {"id": "SORXX/125830/SORKM_125830_2021Y10M31D_00H38M14S_img", "annotations": [], "attr": {"frame": 7}}, {"id": "SORXX/125830/SORKM_125830_2021Y10M31D_13H23M28S_img", "annotations": [], "attr": {"frame": 8}}, {"id": "SORXX/125830/SORKM_125830_2021Y11M01D_01H22M11S_img", "annotations": [], "attr": {"frame": 9}}, {"id": "SORXX/125830/SORKM_125830_2021Y11M01D_12H57M23S_img", "annotations": [], "attr": {"frame": 10}}, {"id": "SORXX/125830/SORKM_125830_2021Y11M01D_16H57M11S_img", "annotations": [], "attr": {"frame": 11}}, {"id": "SORXX/125830/SORKM_125830_2021Y11M02D_00H15M21S_img", "annotations": [], "attr": {"frame": 12}}, {"id": "SORXX/125830/SORKM_125830_2021Y11M02D_08H23M07S_img", "annotations": [{"id": 0, "type": "bbox", "attributes": {"occluded": false, "rotation": 0.0, "track_id": 4, "keyframe": true}, "group": 0, "label_id": 0, "z_order": 0, "bbox": [1249.54, 1184.49, 44.82999999999993, 17.49000000000001]}], "attr": {"frame": 13}}, {"id": "SORXX/125830/SORKM_125830_2021Y11M02D_15H42M21S_img", "annotations": [{"id": 0, "type": "bbox", "attributes": {"occluded": false, "rotation": 0.0, "track_id": 4, "keyframe": true}, "group": 0, "label_id": 0, "z_order": 0, "bbox": [1239.7, 1170.75, 61.399999999999864, 31.950000000000045]}], "attr": {"frame": 14}}, {"id": "SORXX/125830/SORKM_125830_2021Y11M03D_01H29M11S_img", "annotations": [{"id": 0, "type": "bbox", "attributes": {"occluded": false, "rotation": 0.0, "track_id": 0, "keyframe": true}, "group": 0, "label_id": 0, "z_order": 0, "bbox": [555.24, 1458.12, 13.909999999999968, 15.650000000000091]}, {"id": 0, "type": "bbox", "attributes": {"occluded": false, "rotation": 0.0, "track_id": 2, "keyframe": true}, "group": 0, "label_id": 0, "z_order": 0, "bbox": [1787.42, 1490.41, 15.049999999999955, 15.049999999999955]}, {"id": 0, "type": "bbox", "attributes": {"occluded": false, "rotation": 0.0, "track_id": 4, "keyframe": true}, "group": 0, "label_id": 0, "z_order": 0, "bbox": [1238.8, 1167.28, 72.70000000000005, 42.22000000000003]}], "attr": {"frame": 15}}, {"id": "SORXX/125830/SORKM_125830_2021Y11M03D_12H18M54S_img", "annotations": [{"id": 0, "type": "bbox", "attributes": {"occluded": false, "rotation": 0.0, "track_id": 0, "keyframe": true}, "group": 0, "label_id": 0, "z_order": 0, "bbox": [552.46, 1454.0, 15.339999999999918, 15.25]}, {"id": 0, "type": "bbox", "attributes": {"occluded": false, "rotation": 0.0, "track_id": 2, "keyframe": true}, "group": 0, "label_id": 0, "z_order": 0, "bbox": [1791.72, 1487.9, 12.879999999999882, 12.549999999999955]}, {"id": 0, "type": "bbox", "attributes": {"occluded": false, "rotation": 0.0, "track_id": 4, "keyframe": true}, "group": 0, "label_id": 0, "z_order": 0, "bbox": [1237.4, 1158.17, 83.20999999999981, 45.929999999999836]}], "attr": {"frame": 16}}, {"id": "SORXX/125830/SORKM_125830_2021Y11M03D_16H11M45S_img", "annotations": [{"id": 0, "type": "bbox", "attributes": {"occluded": false, "rotation": 0.0, "track_id": 0, "keyframe": true}, "group": 0, "label_id": 0, "z_order": 0, "bbox": [550.38, 1455.39, 17.120000000000005, 17.00999999999999]}, {"id": 0, "type": "bbox", "attributes": {"occluded": false, "rotation": 0.0, "track_id": 2, "keyframe": true}, "group": 0, "label_id": 0, "z_order": 0, "bbox": [1784.56, 1488.6, 16.1400000000001, 14.350000000000136]}, {"id": 0, "type": "bbox", "attributes": {"occluded": false, "rotation": 0.0, "track_id": 4, "keyframe": true}, "group": 0, "label_id": 0, "z_order": 0, "bbox": [1232.3, 1154.87, 88.09000000000015, 53.23000000000002]}], "attr": {"frame": 17}}, {"id": "SORXX/125830/SORKM_125830_2021Y11M04D_00H23M42S_img", "annotations": [{"id": 0, "type": "bbox", "attributes": {"occluded": false, "rotation": 0.0, "track_id": 0, "keyframe": true}, "group": 0, "label_id": 0, "z_order": 0, "bbox": [556.29, 1460.6, 17.81000000000006, 18.75]}, {"id": 0, "type": "bbox", "attributes": {"occluded": false, "rotation": 0.0, "track_id": 1, "keyframe": true}, "group": 0, "label_id": 0, "z_order": 0, "bbox": [593.06, 807.84, 8.950000000000045, 9.5]}, {"id": 0, "type": "bbox", "attributes": {"occluded": false, "rotation": 0.0, "track_id": 2, "keyframe": true}, "group": 0, "label_id": 0, "z_order": 0, "bbox": [1787.72, 1497.1, 17.180000000000064, 14.6400000000001]}, {"id": 0, "type": "bbox", "attributes": {"occluded": false, "rotation": 0.0, "track_id": 4, "keyframe": true}, "group": 0, "label_id": 0, "z_order": 0, "bbox": [1257.3, 1146.96, 69.68000000000006, 50.13999999999987]}], "attr": {"frame": 18}}, {"id": "SORXX/125830/SORKM_125830_2021Y11M04D_13H16M42S_img", "annotations": [{"id": 0, "type": "bbox", "attributes": {"occluded": false, "rotation": 0.0, "track_id": 0, "keyframe": true}, "group": 0, "label_id": 0, "z_order": 0, "bbox": [553.51, 1443.27, 24.789999999999964, 29.829999999999927]}, {"id": 0, "type": "bbox", "attributes": {"occluded": false, "rotation": 0.0, "track_id": 1, "keyframe": true}, "group": 0, "label_id": 0, "z_order": 0, "bbox": [590.69, 793.73, 9.809999999999945, 10.370000000000005]}, {"id": 0, "type": "bbox", "attributes": {"occluded": false, "rotation": 0.0, "track_id": 2, "keyframe": true}, "group": 0, "label_id": 0, "z_order": 0, "bbox": [1785.13, 1487.3, 16.069999999999936, 13.6400000000001]}, {"id": 0, "type": "bbox", "attributes": {"occluded": false, "rotation": 0.0, "track_id": 4, "keyframe": true}, "group": 0, "label_id": 0, "z_order": 0, "bbox": [1246.5, 1125.87, 90.36999999999989, 63.330000000000155]}], "attr": {"frame": 19}}, {"id": "SORXX/125830/SORKM_125830_2021Y11M04D_17H39M39S_img", "annotations": [{"id": 0, "type": "bbox", "attributes": {"occluded": false, "rotation": 0.0, "track_id": 0, "keyframe": true}, "group": 0, "label_id": 0, "z_order": 0, "bbox": [555.94, 1450.18, 24.839999999999918, 22.220000000000027]}, {"id": 0, "type": "bbox", "attributes": {"occluded": false, "rotation": 0.0, "track_id": 1, "keyframe": true}, "group": 0, "label_id": 0, "z_order": 0, "bbox": [588.31, 794.42, 9.81000000000006, 10.379999999999995]}, {"id": 0, "type": "bbox", "attributes": {"occluded": false, "rotation": 0.0, "track_id": 2, "keyframe": true}, "group": 0, "label_id": 0, "z_order": 0, "bbox": [1781.53, 1483.3, 18.470000000000027, 13.600000000000136]}, {"id": 0, "type": "bbox", "attributes": {"occluded": false, "rotation": 0.0, "track_id": 4, "keyframe": true}, "group": 0, "label_id": 0, "z_order": 0, "bbox": [1246.9, 1118.62, 90.84999999999991, 70.7800000000002]}], "attr": {"frame": 20}}, {"id": "SORXX/125830/SORKM_125830_2021Y11M05D_01H06M00S_img", "annotations": [{"id": 0, "type": "bbox", "attributes": {"occluded": false, "rotation": 0.0, "track_id": 0, "keyframe": true}, "group": 0, "label_id": 0, "z_order": 0, "bbox": [554.55, 1450.2, 25.550000000000068, 23.24000000000001]}, {"id": 0, "type": "bbox", "attributes": {"occluded": false, "rotation": 0.0, "track_id": 1, "keyframe": true}, "group": 0, "label_id": 0, "z_order": 0, "bbox": [587.89, 799.45, 10.509999999999991, 10.349999999999909]}, {"id": 0, "type": "bbox", "attributes": {"occluded": false, "rotation": 0.0, "track_id": 2, "keyframe": true}, "group": 0, "label_id": 0, "z_order": 0, "bbox": [1779.37, 1486.61, 21.930000000000064, 16.3900000000001]}, {"id": 0, "type": "bbox", "attributes": {"occluded": false, "rotation": 0.0, "track_id": 4, "keyframe": true}, "group": 0, "label_id": 0, "z_order": 0, "bbox": [1247.3, 1113.79, 102.52999999999997, 83.50999999999999]}], "attr": {"frame": 21}}, {"id": "SORXX/125830/SORKM_125830_2021Y11M05D_08H50M50S_img", "annotations": [{"id": 0, "type": "bbox", "attributes": {"occluded": false, "rotation": 0.0, "track_id": 0, "keyframe": true}, "group": 0, "label_id": 0, "z_order": 0, "bbox": [550.38, 1454.0, 25.220000000000027, 22.569999999999936]}, {"id": 0, "type": "bbox", "attributes": {"occluded": false, "rotation": 0.0, "track_id": 1, "keyframe": true}, "group": 0, "label_id": 0, "z_order": 0, "bbox": [585.24, 796.66, 9.759999999999991, 9.040000000000077]}, {"id": 0, "type": "bbox", "attributes": {"occluded": false, "rotation": 0.0, "track_id": 2, "keyframe": true}, "group": 0, "label_id": 0, "z_order": 0, "bbox": [1776.49, 1478.12, 21.50999999999999, 27.080000000000155]}, {"id": 0, "type": "bbox", "attributes": {"occluded": false, "rotation": 0.0, "track_id": 4, "keyframe": true}, "group": 0, "label_id": 0, "z_order": 0, "bbox": [1244.2, 1110.05, 117.04999999999995, 88.75]}], "attr": {"frame": 22}}, {"id": "SORXX/125830/SORKM_125830_2021Y11M05D_12H49M54S_img", "annotations": [{"id": 0, "type": "bbox", "attributes": {"occluded": false, "rotation": 0.0, "track_id": 0, "keyframe": true}, "group": 0, "label_id": 0, "z_order": 0, "bbox": [555.94, 1437.0, 21.75999999999999, 29.839999999999918]}, {"id": 0, "type": "bbox", "attributes": {"occluded": false, "rotation": 0.0, "track_id": 1, "keyframe": true}, "group": 0, "label_id": 0, "z_order": 0, "bbox": [590.83, 796.8, 10.569999999999936, 10.900000000000091]}, {"id": 0, "type": "bbox", "attributes": {"occluded": false, "rotation": 0.0, "track_id": 2, "keyframe": true}, "group": 0, "label_id": 0, "z_order": 0, "bbox": [1775.63, 1482.6, 28.169999999999845, 19.580000000000155]}, {"id": 0, "type": "bbox", "attributes": {"occluded": false, "rotation": 0.0, "track_id": 4, "keyframe": true}, "group": 0, "label_id": 0, "z_order": 0, "bbox": [1242.7, 1096.65, 112.83999999999992, 105.04999999999995]}], "attr": {"frame": 23}}, {"id": "SORXX/125830/SORKM_125830_2021Y11M06D_01H41M05S_img", "annotations": [{"id": 0, "type": "bbox", "attributes": {"occluded": false, "rotation": 0.0, "track_id": 0, "keyframe": true}, "group": 0, "label_id": 0, "z_order": 0, "bbox": [556.98, 1430.4, 26.620000000000005, 37.82999999999993]}, {"id": 0, "type": "bbox", "attributes": {"occluded": false, "rotation": 0.0, "track_id": 1, "keyframe": true}, "group": 0, "label_id": 0, "z_order": 0, "bbox": [589.29, 796.38, 11.710000000000036, 12.620000000000005]}, {"id": 0, "type": "bbox", "attributes": {"occluded": false, "rotation": 0.0, "track_id": 2, "keyframe": true}, "group": 0, "label_id": 0, "z_order": 0, "bbox": [1737.04, 1482.89, 61.25999999999999, 19.569999999999936]}, {"id": 0, "type": "bbox", "attributes": {"occluded": false, "rotation": 0.0, "track_id": 4, "keyframe": true}, "group": 0, "label_id": 0, "z_order": 0, "bbox": [1238.1, 1074.46, 125.57000000000016, 128.13999999999987]}], "attr": {"frame": 24}}, {"id": "SORXX/125830/SORKM_125830_2021Y11M06D_12H16M16S_img", "annotations": [{"id": 0, "type": "bbox", "attributes": {"occluded": false, "rotation": 0.0, "track_id": 0, "keyframe": true}, "group": 0, "label_id": 0, "z_order": 0, "bbox": [556.29, 1421.0, 31.81000000000006, 48.26999999999998]}, {"id": 0, "type": "bbox", "attributes": {"occluded": false, "rotation": 0.0, "track_id": 1, "keyframe": true}, "group": 0, "label_id": 0, "z_order": 0, "bbox": [588.87, 793.03, 15.230000000000018, 14.269999999999982]}, {"id": 0, "type": "bbox", "attributes": {"occluded": false, "rotation": 0.0, "track_id": 2, "keyframe": true}, "group": 0, "label_id": 0, "z_order": 0, "bbox": [1733.29, 1485.0, 64.30999999999995, 25.529999999999973]}, {"id": 0, "type": "bbox", "attributes": {"occluded": false, "rotation": 0.0, "track_id": 3, "keyframe": true}, "group": 0, "label_id": 0, "z_order": 0, "bbox": [1787.29, 714.06, 8.340000000000146, 16.270000000000095]}, {"id": 0, "type": "bbox", "attributes": {"occluded": false, "rotation": 0.0, "track_id": 4, "keyframe": true}, "group": 0, "label_id": 0, "z_order": 0, "bbox": [1255.7, 1059.74, 107.52999999999997, 132.55999999999995]}], "attr": {"frame": 25}}, {"id": "SORXX/125830/SORKM_125830_2021Y11M07D_00H43M38S_img", "annotations": [{"id": 0, "type": "bbox", "attributes": {"occluded": false, "rotation": 0.0, "track_id": 0, "keyframe": true}, "group": 0, "label_id": 0, "z_order": 0, "bbox": [554.9, 1403.6, 29.399999999999977, 68.45000000000005]}, {"id": 0, "type": "bbox", "attributes": {"occluded": false, "rotation": 0.0, "track_id": 1, "keyframe": true}, "group": 0, "label_id": 0, "z_order": 0, "bbox": [586.92, 797.36, 15.879999999999995, 20.539999999999964]}, {"id": 0, "type": "bbox", "attributes": {"occluded": false, "rotation": 0.0, "track_id": 2, "keyframe": true}, "group": 0, "label_id": 0, "z_order": 0, "bbox": [1718.98, 1488.7, 73.42000000000007, 37.37999999999988]}, {"id": 0, "type": "bbox", "attributes": {"occluded": false, "rotation": 0.0, "track_id": 3, "keyframe": true}, "group": 0, "label_id": 0, "z_order": 0, "bbox": [1780.04, 718.4, 10.059999999999945, 16.50999999999999]}, {"id": 0, "type": "bbox", "attributes": {"occluded": false, "rotation": 0.0, "track_id": 4, "keyframe": true}, "group": 0, "label_id": 0, "z_order": 0, "bbox": [1245.4, 1052.15, 122.38999999999987, 156.04999999999995]}], "attr": {"frame": 26}}, {"id": "SORXX/125830/SORKM_125830_2021Y11M07D_13H28M44S_img", "annotations": [{"id": 0, "type": "bbox", "attributes": {"occluded": false, "rotation": 0.0, "track_id": 0, "keyframe": true}, "group": 0, "label_id": 0, "z_order": 0, "bbox": [542.38, 1392.47, 39.51999999999998, 72.62999999999988]}, {"id": 0, "type": "bbox", "attributes": {"occluded": false, "rotation": 0.0, "track_id": 1, "keyframe": true}, "group": 0, "label_id": 0, "z_order": 0, "bbox": [585.38, 788.84, 18.220000000000027, 18.559999999999945]}, {"id": 0, "type": "bbox", "attributes": {"occluded": false, "rotation": 0.0, "track_id": 2, "keyframe": true}, "group": 0, "label_id": 0, "z_order": 0, "bbox": [1707.17, 1478.5, 85.42999999999984, 54.42000000000007]}, {"id": 0, "type": "bbox", "attributes": {"occluded": false, "rotation": 0.0, "track_id": 3, "keyframe": true}, "group": 0, "label_id": 0, "z_order": 0, "bbox": [1777.39, 712.37, 13.929999999999836, 18.200000000000045]}, {"id": 0, "type": "bbox", "attributes": {"occluded": false, "rotation": 0.0, "track_id": 4, "keyframe": true}, "group": 0, "label_id": 0, "z_order": 0, "bbox": [1241.9, 1028.11, 116.70999999999981, 169.2900000000002]}], "attr": {"frame": 27}}, {"id": "SORXX/125830/SORKM_125830_2021Y11M07D_17H28M07S_img", "annotations": [{"id": 0, "type": "bbox", "attributes": {"occluded": false, "rotation": 0.0, "track_id": 0, "keyframe": true}, "group": 0, "label_id": 0, "z_order": 0, "bbox": [539.95, 1397.34, 42.64999999999998, 76.46000000000004]}, {"id": 0, "type": "bbox", "attributes": {"occluded": false, "rotation": 0.0, "track_id": 1, "keyframe": true}, "group": 0, "label_id": 0, "z_order": 0, "bbox": [584.82, 797.22, 18.479999999999905, 19.379999999999995]}, {"id": 0, "type": "bbox", "attributes": {"occluded": false, "rotation": 0.0, "track_id": 2, "keyframe": true}, "group": 0, "label_id": 0, "z_order": 0, "bbox": [1693.06, 1485.3, 96.03999999999996, 57.99000000000001]}, {"id": 0, "type": "bbox", "attributes": {"occluded": false, "rotation": 0.0, "track_id": 3, "keyframe": true}, "group": 0, "label_id": 0, "z_order": 0, "bbox": [1773.77, 719.17, 18.029999999999973, 22.25999999999999]}, {"id": 0, "type": "bbox", "attributes": {"occluded": false, "rotation": 0.0, "track_id": 4, "keyframe": true}, "group": 0, "label_id": 0, "z_order": 0, "bbox": [1238.4, 1036.02, 123.68999999999983, 167.07999999999993]}], "attr": {"frame": 28}}, {"id": "SORXX/125830/SORKM_125830_2021Y11M08D_01H17M57S_img", "annotations": [{"id": 0, "type": "bbox", "attributes": {"occluded": false, "rotation": 0.0, "track_id": 0, "keyframe": true}, "group": 0, "label_id": 0, "z_order": 0, "bbox": [543.08, 1399.78, 42.64999999999998, 76.45000000000005]}, {"id": 0, "type": "bbox", "attributes": {"occluded": false, "rotation": 0.0, "track_id": 1, "keyframe": true}, "group": 0, "label_id": 0, "z_order": 0, "bbox": [586.92, 798.62, 19.980000000000018, 20.879999999999995]}, {"id": 0, "type": "bbox", "attributes": {"occluded": false, "rotation": 0.0, "track_id": 2, "keyframe": true}, "group": 0, "label_id": 0, "z_order": 0, "bbox": [1677.54, 1491.2, 114.96000000000004, 58.960000000000036]}, {"id": 0, "type": "bbox", "attributes": {"occluded": false, "rotation": 0.0, "track_id": 3, "keyframe": true}, "group": 0, "label_id": 0, "z_order": 0, "bbox": [1773.77, 723.8, 19.029999999999973, 25.360000000000014]}, {"id": 0, "type": "bbox", "attributes": {"occluded": false, "rotation": 0.0, "track_id": 4, "keyframe": true}, "group": 0, "label_id": 0, "z_order": 0, "bbox": [1237.5, 1036.96, 132.81999999999994, 168.03999999999996]}], "attr": {"frame": 29}}, {"id": "SORXX/125830/SORKM_125830_2021Y11M08D_14H20M47S_img", "annotations": [{"id": 0, "type": "bbox", "attributes": {"occluded": false, "rotation": 0.0, "track_id": 0, "keyframe": true}, "group": 0, "label_id": 0, "z_order": 0, "bbox": [542.73, 1385.87, 50.97000000000003, 107.43000000000006]}, {"id": 0, "type": "bbox", "attributes": {"occluded": false, "rotation": 0.0, "track_id": 1, "keyframe": true}, "group": 0, "label_id": 0, "z_order": 0, "bbox": [587.89, 789.11, 23.31000000000006, 21.49000000000001]}, {"id": 0, "type": "bbox", "attributes": {"occluded": false, "rotation": 0.0, "track_id": 2, "keyframe": true}, "group": 0, "label_id": 0, "z_order": 0, "bbox": [1660.64, 1454.4, 132.65999999999985, 78.04999999999995]}, {"id": 0, "type": "bbox", "attributes": {"occluded": false, "rotation": 0.0, "track_id": 3, "keyframe": true}, "group": 0, "label_id": 0, "z_order": 0, "bbox": [1796.7, 718.5, 21.200000000000045, 32.59000000000003]}, {"id": 0, "type": "bbox", "attributes": {"occluded": false, "rotation": 0.0, "track_id": 4, "keyframe": true}, "group": 0, "label_id": 0, "z_order": 0, "bbox": [1235.92, 1118.27, 50.57999999999993, 36.13000000000011]}], "attr": {"frame": 30}}, {"id": "SORXX/125830/SORKM_125830_2021Y11M08D_18H29M15S_img", "annotations": [{"id": 0, "type": "bbox", "attributes": {"occluded": false, "rotation": 0.0, "track_id": 0, "keyframe": true}, "group": 0, "label_id": 0, "z_order": 0, "bbox": [540.64, 1388.65, 54.75999999999999, 108.44999999999982]}, {"id": 0, "type": "bbox", "attributes": {"occluded": false, "rotation": 0.0, "track_id": 1, "keyframe": true}, "group": 0, "label_id": 0, "z_order": 0, "bbox": [585.8, 792.75, 23.700000000000045, 23.75]}, {"id": 0, "type": "bbox", "attributes": {"occluded": false, "rotation": 0.0, "track_id": 2, "keyframe": true}, "group": 0, "label_id": 0, "z_order": 0, "bbox": [1661.44, 1455.8, 131.8599999999999, 78.46000000000004]}, {"id": 0, "type": "bbox", "attributes": {"occluded": false, "rotation": 0.0, "track_id": 3, "keyframe": true}, "group": 0, "label_id": 0, "z_order": 0, "bbox": [1795.25, 723.1, 23.84999999999991, 33.299999999999955]}, {"id": 0, "type": "bbox", "attributes": {"occluded": false, "rotation": 0.0, "track_id": 4, "keyframe": true}, "group": 0, "label_id": 0, "z_order": 0, "bbox": [1233.39, 1123.96, 55.00999999999999, 38.940000000000055]}], "attr": {"frame": 31}}, {"id": "SORXX/125830/SORKM_125830_2021Y11M09D_00H36M50S_img", "annotations": [{"id": 0, "type": "bbox", "attributes": {"occluded": false, "rotation": 0.0, "track_id": 0, "keyframe": true}, "group": 0, "label_id": 0, "z_order": 0, "bbox": [543.77, 1398.73, 56.83000000000004, 114.36999999999989]}, {"id": 0, "type": "bbox", "attributes": {"occluded": false, "rotation": 0.0, "track_id": 1, "keyframe": true}, "group": 0, "label_id": 0, "z_order": 0, "bbox": [586.91, 803.92, 23.389999999999986, 22.780000000000086]}, {"id": 0, "type": "bbox", "attributes": {"occluded": false, "rotation": 0.0, "track_id": 2, "keyframe": true}, "group": 0, "label_id": 0, "z_order": 0, "bbox": [1663.05, 1459.6, 131.04999999999995, 79.29000000000019]}, {"id": 0, "type": "bbox", "attributes": {"occluded": false, "rotation": 0.0, "track_id": 3, "keyframe": true}, "group": 0, "label_id": 0, "z_order": 0, "bbox": [1797.43, 733.0, 23.86999999999989, 35.23000000000002]}, {"id": 0, "type": "bbox", "attributes": {"occluded": false, "rotation": 0.0, "track_id": 4, "keyframe": true}, "group": 0, "label_id": 0, "z_order": 0, "bbox": [1234.97, 1132.19, 54.32999999999993, 38.309999999999945]}], "attr": {"frame": 32}}, {"id": "SORXX/125830/SORKM_125830_2021Y11M09D_08H36M18S_img", "annotations": [{"id": 0, "type": "bbox", "attributes": {"occluded": false, "rotation": 0.0, "track_id": 0, "keyframe": true}, "group": 0, "label_id": 0, "z_order": 0, "bbox": [543.08, 1389.34, 65.51999999999998, 122.06000000000017]}, {"id": 0, "type": "bbox", "attributes": {"occluded": false, "rotation": 0.0, "track_id": 1, "keyframe": true}, "group": 0, "label_id": 0, "z_order": 0, "bbox": [585.95, 797.89, 27.25, 22.31000000000006]}, {"id": 0, "type": "bbox", "attributes": {"occluded": false, "rotation": 0.0, "track_id": 2, "keyframe": true}, "group": 0, "label_id": 0, "z_order": 0, "bbox": [1647.76, 1447.3, 142.94000000000005, 75.90000000000009]}, {"id": 0, "type": "bbox", "attributes": {"occluded": false, "rotation": 0.0, "track_id": 3, "keyframe": true}, "group": 0, "label_id": 0, "z_order": 0, "bbox": [1791.63, 729.6, 28.4699999999998, 40.319999999999936]}, {"id": 0, "type": "bbox", "attributes": {"occluded": false, "rotation": 0.0, "track_id": 4, "keyframe": true}, "group": 0, "label_id": 0, "z_order": 0, "bbox": [1233.07, 1127.13, 52.430000000000064, 37.9699999999998]}], "attr": {"frame": 33}}, {"id": "SORXX/125830/SORKM_125830_2021Y11M09D_17H11M21S_img", "annotations": [{"id": 0, "type": "bbox", "attributes": {"occluded": false, "rotation": 0.0, "track_id": 0, "keyframe": true}, "group": 0, "label_id": 0, "z_order": 0, "bbox": [546.21, 1381.7, 72.08999999999992, 135.5999999999999]}, {"id": 0, "type": "bbox", "attributes": {"occluded": false, "rotation": 0.0, "track_id": 1, "keyframe": true}, "group": 0, "label_id": 0, "z_order": 0, "bbox": [585.46, 798.13, 31.839999999999918, 24.269999999999982]}, {"id": 0, "type": "bbox", "attributes": {"occluded": false, "rotation": 0.0, "track_id": 2, "keyframe": true}, "group": 0, "label_id": 0, "z_order": 0, "bbox": [1636.9, 1448.3, 153.5999999999999, 69.83000000000015]}, {"id": 0, "type": "bbox", "attributes": {"occluded": false, "rotation": 0.0, "track_id": 3, "keyframe": true}, "group": 0, "label_id": 0, "z_order": 0, "bbox": [1788.74, 729.4, 38.16000000000008, 54.75999999999999]}, {"id": 0, "type": "bbox", "attributes": {"occluded": false, "rotation": 0.0, "track_id": 4, "keyframe": true}, "group": 0, "label_id": 0, "z_order": 0, "bbox": [1232.12, 1125.86, 52.48000000000002, 37.97000000000003]}], "attr": {"frame": 34}}, {"id": "SORXX/125830/SORKM_125830_2021Y11M10D_01H40M02S_img", "annotations": [{"id": 0, "type": "bbox", "attributes": {"occluded": false, "rotation": 0.0, "track_id": 0, "keyframe": true}, "group": 0, "label_id": 0, "z_order": 0, "bbox": [543.77, 1376.48, 84.63, 137.72000000000003]}, {"id": 0, "type": "bbox", "attributes": {"occluded": false, "rotation": 0.0, "track_id": 1, "keyframe": true}, "group": 0, "label_id": 0, "z_order": 0, "bbox": [585.46, 798.13, 32.539999999999964, 24.07000000000005]}, {"id": 0, "type": "bbox", "attributes": {"occluded": false, "rotation": 0.0, "track_id": 2, "keyframe": true}, "group": 0, "label_id": 0, "z_order": 0, "bbox": [1632.55, 1449.5, 164.04999999999995, 60.5]}, {"id": 0, "type": "bbox", "attributes": {"occluded": false, "rotation": 0.0, "track_id": 3, "keyframe": true}, "group": 0, "label_id": 0, "z_order": 0, "bbox": [1788.25, 728.7, 40.84999999999991, 58.59999999999991]}, {"id": 0, "type": "bbox", "attributes": {"occluded": false, "rotation": 0.0, "track_id": 4, "keyframe": true}, "group": 0, "label_id": 0, "z_order": 0, "bbox": [1230.22, 1123.02, 56.27999999999997, 36.98000000000002]}], "attr": {"frame": 35}}, {"id": "SORXX/125830/SORKM_125830_2021Y11M10D_08H15M24S_img", "annotations": [{"id": 0, "type": "bbox", "attributes": {"occluded": false, "rotation": 0.0, "track_id": 0, "keyframe": true}, "group": 0, "label_id": 0, "z_order": 0, "bbox": [543.42, 1378.57, 85.28000000000009, 145.33000000000015]}, {"id": 0, "type": "bbox", "attributes": {"occluded": false, "rotation": 0.0, "track_id": 1, "keyframe": true}, "group": 0, "label_id": 0, "z_order": 0, "bbox": [584.98, 799.1, 33.01999999999998, 26.0]}, {"id": 0, "type": "bbox", "attributes": {"occluded": false, "rotation": 0.0, "track_id": 2, "keyframe": true}, "group": 0, "label_id": 0, "z_order": 0, "bbox": [1626.18, 1446.6, 167.22000000000003, 66.0]}, {"id": 0, "type": "bbox", "attributes": {"occluded": false, "rotation": 0.0, "track_id": 3, "keyframe": true}, "group": 0, "label_id": 0, "z_order": 0, "bbox": [1786.32, 735.9, 41.38000000000011, 66.13]}, {"id": 0, "type": "bbox", "attributes": {"occluded": false, "rotation": 0.0, "track_id": 4, "keyframe": true}, "group": 0, "label_id": 0, "z_order": 0, "bbox": [1230.86, 1126.18, 56.940000000000055, 37.319999999999936]}], "attr": {"frame": 36}}, {"id": "SORXX/125830/SORKM_125830_2021Y11M10D_12H15M18S_img", "annotations": [{"id": 0, "type": "bbox", "attributes": {"occluded": false, "rotation": 0.0, "track_id": 0, "keyframe": true}, "group": 0, "label_id": 0, "z_order": 0, "bbox": [544.12, 1367.79, 92.58000000000004, 146.71000000000004]}, {"id": 0, "type": "bbox", "attributes": {"occluded": false, "rotation": 0.0, "track_id": 1, "keyframe": true}, "group": 0, "label_id": 0, "z_order": 0, "bbox": [584.98, 788.47, 33.01999999999998, 26.529999999999973]}, {"id": 0, "type": "bbox", "attributes": {"occluded": false, "rotation": 0.0, "track_id": 2, "keyframe": true}, "group": 0, "label_id": 0, "z_order": 0, "bbox": [1621.83, 1429.8, 169.57000000000016, 72.70000000000005]}, {"id": 0, "type": "bbox", "attributes": {"occluded": false, "rotation": 0.0, "track_id": 3, "keyframe": true}, "group": 0, "label_id": 0, "z_order": 0, "bbox": [1785.6, 722.9, 46.200000000000045, 78.88999999999999]}, {"id": 0, "type": "bbox", "attributes": {"occluded": false, "rotation": 0.0, "track_id": 4, "keyframe": true}, "group": 0, "label_id": 0, "z_order": 0, "bbox": [1227.69, 1114.79, 57.309999999999945, 37.309999999999945]}], "attr": {"frame": 37}}, {"id": "SORXX/125830/SORKM_125830_2021Y11M10D_16H15M19S_img", "annotations": [{"id": 0, "type": "bbox", "attributes": {"occluded": false, "rotation": 0.0, "track_id": 0, "keyframe": true}, "group": 0, "label_id": 0, "z_order": 0, "bbox": [543.42, 1373.0, 109.58000000000004, 145.70000000000005]}, {"id": 0, "type": "bbox", "attributes": {"occluded": false, "rotation": 0.0, "track_id": 1, "keyframe": true}, "group": 0, "label_id": 0, "z_order": 0, "bbox": [585.71, 791.13, 35.18999999999994, 27.970000000000027]}, {"id": 0, "type": "bbox", "attributes": {"occluded": false, "rotation": 0.0, "track_id": 2, "keyframe": true}, "group": 0, "label_id": 0, "z_order": 0, "bbox": [1618.35, 1433.86, 174.25, 74.44000000000005]}, {"id": 0, "type": "bbox", "attributes": {"occluded": false, "rotation": 0.0, "track_id": 3, "keyframe": true}, "group": 0, "label_id": 0, "z_order": 0, "bbox": [1783.9, 730.63, 47.419999999999845, 83.66999999999996]}, {"id": 0, "type": "bbox", "attributes": {"occluded": false, "rotation": 0.0, "track_id": 4, "keyframe": true}, "group": 0, "label_id": 0, "z_order": 0, "bbox": [1226.75, 1118.27, 55.450000000000045, 37.32999999999993]}], "attr": {"frame": 38}}, {"id": "SORXX/125830/SORKM_125830_2021Y11M11D_00H42M23S_img", "annotations": [{"id": 0, "type": "bbox", "attributes": {"occluded": false, "rotation": 0.0, "track_id": 0, "keyframe": true}, "group": 0, "label_id": 0, "z_order": 0, "bbox": [550.72, 1377.87, 124.48000000000002, 155.73000000000002]}, {"id": 0, "type": "bbox", "attributes": {"occluded": false, "rotation": 0.0, "track_id": 1, "keyframe": true}, "group": 0, "label_id": 0, "z_order": 0, "bbox": [586.67, 793.06, 37.129999999999995, 27.970000000000027]}, {"id": 0, "type": "bbox", "attributes": {"occluded": false, "rotation": 0.0, "track_id": 2, "keyframe": true}, "group": 0, "label_id": 0, "z_order": 0, "bbox": [1622.7, 1437.04, 172.20000000000005, 76.75999999999999]}, {"id": 0, "type": "bbox", "attributes": {"occluded": false, "rotation": 0.0, "track_id": 3, "keyframe": true}, "group": 0, "label_id": 0, "z_order": 0, "bbox": [1783.9, 730.63, 47.419999999999845, 95.97000000000003]}, {"id": 0, "type": "bbox", "attributes": {"occluded": false, "rotation": 0.0, "track_id": 4, "keyframe": true}, "group": 0, "label_id": 0, "z_order": 0, "bbox": [1230.23, 1123.02, 55.450000000000045, 37.32999999999993]}], "attr": {"frame": 39}}, {"id": "SORXX/125830/SORKM_125830_2021Y11M11D_17H42M36S_img", "annotations": [{"id": 0, "type": "bbox", "attributes": {"occluded": false, "rotation": 0.0, "track_id": 0, "keyframe": true}, "group": 0, "label_id": 0, "z_order": 0, "bbox": [558.03, 1378.57, 165.87, 167.23000000000002]}, {"id": 0, "type": "bbox", "attributes": {"occluded": false, "rotation": 0.0, "track_id": 1, "keyframe": true}, "group": 0, "label_id": 0, "z_order": 0, "bbox": [589.02, 783.2, 41.180000000000064, 30.789999999999964]}, {"id": 0, "type": "bbox", "attributes": {"occluded": false, "rotation": 0.0, "track_id": 2, "keyframe": true}, "group": 0, "label_id": 0, "z_order": 0, "bbox": [1650.8, 1419.66, 145.79999999999995, 89.83999999999992]}, {"id": 0, "type": "bbox", "attributes": {"occluded": false, "rotation": 0.0, "track_id": 3, "keyframe": true}, "group": 0, "label_id": 0, "z_order": 0, "bbox": [1783.9, 724.8, 44.5, 106.90000000000009]}, {"id": 0, "type": "bbox", "attributes": {"occluded": false, "rotation": 0.0, "track_id": 4, "keyframe": true}, "group": 0, "label_id": 0, "z_order": 0, "bbox": [1219.15, 1116.37, 69.04999999999995, 41.73000000000002]}], "attr": {"frame": 40}}, {"id": "SORXX/125830/SORKM_125830_2021Y11M12D_01H31M28S_img", "annotations": [{"id": 0, "type": "bbox", "attributes": {"occluded": false, "rotation": 0.0, "track_id": 0, "keyframe": true}, "group": 0, "label_id": 0, "z_order": 0, "bbox": [556.36, 1384.41, 190.03999999999996, 175.99]}, {"id": 0, "type": "bbox", "attributes": {"occluded": false, "rotation": 0.0, "track_id": 1, "keyframe": true}, "group": 0, "label_id": 0, "z_order": 0, "bbox": [587.85, 785.84, 40.879999999999995, 28.480000000000018]}, {"id": 0, "type": "bbox", "attributes": {"occluded": false, "rotation": 0.0, "track_id": 2, "keyframe": true}, "group": 0, "label_id": 0, "z_order": 0, "bbox": [1653.99, 1419.95, 143.51, 87.54999999999995]}, {"id": 0, "type": "bbox", "attributes": {"occluded": false, "rotation": 0.0, "track_id": 3, "keyframe": true}, "group": 0, "label_id": 0, "z_order": 0, "bbox": [1779.6, 727.2, 46.100000000000136, 104.69999999999993]}, {"id": 0, "type": "bbox", "attributes": {"occluded": false, "rotation": 0.0, "track_id": 4, "keyframe": true}, "group": 0, "label_id": 0, "z_order": 0, "bbox": [1222.0, 1119.54, 66.79999999999995, 42.960000000000036]}], "attr": {"frame": 41}}, {"id": "SORXX/125830/SORKM_125830_2021Y11M12D_09H02M26S_img", "annotations": [{"id": 0, "type": "bbox", "attributes": {"occluded": false, "rotation": 0.0, "track_id": 0, "keyframe": true}, "group": 0, "label_id": 0, "z_order": 0, "bbox": [552.6, 1390.67, 216.69999999999993, 176.82999999999993]}, {"id": 0, "type": "bbox", "attributes": {"occluded": false, "rotation": 0.0, "track_id": 1, "keyframe": true}, "group": 0, "label_id": 0, "z_order": 0, "bbox": [586.17, 785.5, 40.83000000000004, 29.83000000000004]}, {"id": 0, "type": "bbox", "attributes": {"occluded": false, "rotation": 0.0, "track_id": 2, "keyframe": true}, "group": 0, "label_id": 0, "z_order": 0, "bbox": [1653.99, 1418.5, 141.80999999999995, 87.0]}, {"id": 0, "type": "bbox", "attributes": {"occluded": false, "rotation": 0.0, "track_id": 3, "keyframe": true}, "group": 0, "label_id": 0, "z_order": 0, "bbox": [1774.0, 727.2, 49.299999999999955, 100.39999999999998]}, {"id": 0, "type": "bbox", "attributes": {"occluded": false, "rotation": 0.0, "track_id": 4, "keyframe": true}, "group": 0, "label_id": 0, "z_order": 0, "bbox": [1220.74, 1120.17, 66.79999999999995, 42.960000000000036]}], "attr": {"frame": 42}}, {"id": "SORXX/125830/SORKM_125830_2021Y11M12D_13H01M53S_img", "annotations": [{"id": 0, "type": "bbox", "attributes": {"occluded": false, "rotation": 0.0, "track_id": 0, "keyframe": true}, "group": 0, "label_id": 0, "z_order": 0, "bbox": [553.44, 1387.75, 231.76, 180.1500000000001]}, {"id": 0, "type": "bbox", "attributes": {"occluded": false, "rotation": 0.0, "track_id": 1, "keyframe": true}, "group": 0, "label_id": 0, "z_order": 0, "bbox": [588.18, 775.7, 42.82000000000005, 35.43999999999994]}, {"id": 0, "type": "bbox", "attributes": {"occluded": false, "rotation": 0.0, "track_id": 2, "keyframe": true}, "group": 0, "label_id": 0, "z_order": 0, "bbox": [1650.51, 1417.8, 152.28999999999996, 87.40000000000009]}, {"id": 0, "type": "bbox", "attributes": {"occluded": false, "rotation": 0.0, "track_id": 3, "keyframe": true}, "group": 0, "label_id": 0, "z_order": 0, "bbox": [1775.9, 721.9, 50.299999999999955, 103.0]}, {"id": 0, "type": "bbox", "attributes": {"occluded": false, "rotation": 0.0, "track_id": 4, "keyframe": true}, "group": 0, "label_id": 0, "z_order": 0, "bbox": [1222.63, 1114.79, 65.86999999999989, 43.61000000000013]}], "attr": {"frame": 43}}, {"id": "SORXX/125830/SORKM_125830_2021Y11M13D_00H35M45S_img", "annotations": [{"id": 0, "type": "bbox", "attributes": {"occluded": false, "rotation": 0.0, "track_id": 0, "keyframe": true}, "group": 0, "label_id": 0, "z_order": 0, "bbox": [545.51, 1395.67, 262.19000000000005, 179.73000000000002]}, {"id": 0, "type": "bbox", "attributes": {"occluded": false, "rotation": 0.0, "track_id": 1, "keyframe": true}, "group": 0, "label_id": 0, "z_order": 0, "bbox": [586.84, 779.1, 42.15999999999997, 36.39999999999998]}, {"id": 0, "type": "bbox", "attributes": {"occluded": false, "rotation": 0.0, "track_id": 2, "keyframe": true}, "group": 0, "label_id": 0, "z_order": 0, "bbox": [1653.29, 1422.67, 190.21000000000004, 84.23000000000002]}, {"id": 0, "type": "bbox", "attributes": {"occluded": false, "rotation": 0.0, "track_id": 3, "keyframe": true}, "group": 0, "label_id": 0, "z_order": 0, "bbox": [1772.04, 728.42, 50.299999999999955, 103.0]}, {"id": 0, "type": "bbox", "attributes": {"occluded": false, "rotation": 0.0, "track_id": 4, "keyframe": true}, "group": 0, "label_id": 0, "z_order": 0, "bbox": [1219.79, 1120.49, 67.11000000000013, 43.91000000000008]}], "attr": {"frame": 44}}, {"id": "SORXX/125830/SORKM_125830_2021Y11M13D_12H35M32S_img", "annotations": [{"id": 0, "type": "bbox", "attributes": {"occluded": false, "rotation": 0.0, "track_id": 0, "keyframe": true}, "group": 0, "label_id": 0, "z_order": 0, "bbox": [544.09, 1399.84, 309.7099999999999, 178.26]}, {"id": 0, "type": "bbox", "attributes": {"occluded": false, "rotation": 0.0, "track_id": 1, "keyframe": true}, "group": 0, "label_id": 0, "z_order": 0, "bbox": [588.52, 775.2, 44.48000000000002, 37.77999999999997]}, {"id": 0, "type": "bbox", "attributes": {"occluded": false, "rotation": 0.0, "track_id": 2, "keyframe": true}, "group": 0, "label_id": 0, "z_order": 0, "bbox": [1653.29, 1324.3, 267.4100000000001, 182.60000000000014]}, {"id": 0, "type": "bbox", "attributes": {"occluded": false, "rotation": 0.0, "track_id": 3, "keyframe": true}, "group": 0, "label_id": 0, "z_order": 0, "bbox": [1773.49, 726.25, 50.299999999999955, 103.0]}, {"id": 0, "type": "bbox", "attributes": {"occluded": false, "rotation": 0.0, "track_id": 4, "keyframe": true}, "group": 0, "label_id": 0, "z_order": 0, "bbox": [1222.0, 1118.59, 65.79999999999995, 42.31000000000017]}], "attr": {"frame": 45}}, {"id": "SORXX/125830/SORKM_125830_2021Y11M14D_01H11M10S_img", "annotations": [{"id": 0, "type": "bbox", "attributes": {"occluded": false, "rotation": 0.0, "track_id": 0, "keyframe": true}, "group": 0, "label_id": 0, "z_order": 0, "bbox": [537.58, 1399.34, 356.52, 181.86000000000013]}, {"id": 0, "type": "bbox", "attributes": {"occluded": false, "rotation": 0.0, "track_id": 1, "keyframe": true}, "group": 0, "label_id": 0, "z_order": 0, "bbox": [588.52, 772.4, 44.180000000000064, 40.58000000000004]}, {"id": 0, "type": "bbox", "attributes": {"occluded": false, "rotation": 0.0, "track_id": 2, "keyframe": true}, "group": 0, "label_id": 0, "z_order": 0, "bbox": [1653.29, 1167.3, 262.4100000000001, 339.60000000000014]}, {"id": 0, "type": "bbox", "attributes": {"occluded": false, "rotation": 0.0, "track_id": 3, "keyframe": true}, "group": 0, "label_id": 0, "z_order": 0, "bbox": [1772.28, 724.3, 50.819999999999936, 107.12]}, {"id": 0, "type": "bbox", "attributes": {"occluded": false, "rotation": 0.0, "track_id": 4, "keyframe": true}, "group": 0, "label_id": 0, "z_order": 0, "bbox": [1221.7, 1118.59, 64.89999999999986, 40.11000000000013]}], "attr": {"frame": 46}}, {"id": "SORXX/125830/SORKM_125830_2021Y11M14D_13H42M17S_img", "annotations": [{"id": 0, "type": "bbox", "attributes": {"occluded": false, "rotation": 0.0, "track_id": 0, "keyframe": true}, "group": 0, "label_id": 0, "z_order": 0, "bbox": [534.99, 1400.21, 400.61, 174.96000000000004]}, {"id": 0, "type": "bbox", "attributes": {"occluded": false, "rotation": 0.0, "track_id": 1, "keyframe": true}, "group": 0, "label_id": 0, "z_order": 0, "bbox": [588.18, 766.9, 45.32000000000005, 42.56000000000006]}, {"id": 0, "type": "bbox", "attributes": {"occluded": false, "rotation": 0.0, "track_id": 2, "keyframe": true}, "group": 0, "label_id": 0, "z_order": 0, "bbox": [1653.29, 1072.6, 201.41000000000008, 434.3000000000002]}, {"id": 0, "type": "bbox", "attributes": {"occluded": false, "rotation": 0.0, "track_id": 3, "keyframe": true}, "group": 0, "label_id": 0, "z_order": 0, "bbox": [1770.3, 719.5, 51.799999999999955, 109.70000000000005]}, {"id": 0, "type": "bbox", "attributes": {"occluded": false, "rotation": 0.0, "track_id": 4, "keyframe": true}, "group": 0, "label_id": 0, "z_order": 0, "bbox": [1222.33, 1114.79, 65.87000000000012, 40.710000000000036]}], "attr": {"frame": 47}}, {"id": "SORXX/125830/SORKM_125830_2021Y11M14D_17H41M59S_img", "annotations": [{"id": 0, "type": "bbox", "attributes": {"occluded": false, "rotation": 0.0, "track_id": 0, "keyframe": true}, "group": 0, "label_id": 0, "z_order": 0, "bbox": [530.66, 1403.67, 408.44000000000005, 168.02999999999997]}, {"id": 0, "type": "bbox", "attributes": {"occluded": false, "rotation": 0.0, "track_id": 1, "keyframe": true}, "group": 0, "label_id": 0, "z_order": 0, "bbox": [587.85, 769.75, 45.319999999999936, 42.559999999999945]}, {"id": 0, "type": "bbox", "attributes": {"occluded": false, "rotation": 0.0, "track_id": 2, "keyframe": true}, "group": 0, "label_id": 0, "z_order": 0, "bbox": [1653.29, 1073.8, 192.71000000000004, 433.10000000000014]}, {"id": 0, "type": "bbox", "attributes": {"occluded": false, "rotation": 0.0, "track_id": 3, "keyframe": true}, "group": 0, "label_id": 0, "z_order": 0, "bbox": [1768.13, 723.1, 55.86999999999989, 109.95999999999992]}, {"id": 0, "type": "bbox", "attributes": {"occluded": false, "rotation": 0.0, "track_id": 4, "keyframe": true}, "group": 0, "label_id": 0, "z_order": 0, "bbox": [1221.7, 1117.96, 65.20000000000005, 41.940000000000055]}], "attr": {"frame": 48}}, {"id": "SORXX/125830/SORKM_125830_2021Y11M15D_00H12M49S_img", "annotations": [{"id": 0, "type": "bbox", "attributes": {"occluded": false, "rotation": 0.0, "track_id": 0, "keyframe": true}, "group": 0, "label_id": 0, "z_order": 0, "bbox": [527.2, 1409.72, 414.5, 156.77999999999997]}, {"id": 0, "type": "bbox", "attributes": {"occluded": false, "rotation": 0.0, "track_id": 1, "keyframe": true}, "group": 0, "label_id": 0, "z_order": 0, "bbox": [586.67, 778.8, 45.33000000000004, 41.23000000000002]}, {"id": 0, "type": "bbox", "attributes": {"occluded": false, "rotation": 0.0, "track_id": 2, "keyframe": true}, "group": 0, "label_id": 0, "z_order": 0, "bbox": [1654.54, 1075.0, 193.86000000000013, 439.3699999999999]}, {"id": 0, "type": "bbox", "attributes": {"occluded": false, "rotation": 0.0, "track_id": 3, "keyframe": true}, "group": 0, "label_id": 0, "z_order": 0, "bbox": [1764.02, 731.5, 56.38000000000011, 112.90999999999997]}, {"id": 0, "type": "bbox", "attributes": {"occluded": false, "rotation": 0.0, "track_id": 4, "keyframe": true}, "group": 0, "label_id": 0, "z_order": 0, "bbox": [1220.12, 1126.18, 63.580000000000155, 39.11999999999989]}], "attr": {"frame": 49}}, {"id": "SORXX/125830/SORKM_125830_2021Y11M15D_13H15M09S_img", "annotations": [{"id": 0, "type": "bbox", "attributes": {"occluded": false, "rotation": 0.0, "track_id": 0, "keyframe": true}, "group": 0, "label_id": 0, "z_order": 0, "bbox": [527.2, 1406.26, 422.29999999999995, 150.74]}, {"id": 0, "type": "bbox", "attributes": {"occluded": false, "rotation": 0.0, "track_id": 1, "keyframe": true}, "group": 0, "label_id": 0, "z_order": 0, "bbox": [588.85, 769.1, 44.35000000000002, 42.379999999999995]}, {"id": 0, "type": "bbox", "attributes": {"occluded": false, "rotation": 0.0, "track_id": 2, "keyframe": true}, "group": 0, "label_id": 0, "z_order": 0, "bbox": [1668.6, 1064.5, 178.80000000000018, 449.8699999999999]}, {"id": 0, "type": "bbox", "attributes": {"occluded": false, "rotation": 0.0, "track_id": 3, "keyframe": true}, "group": 0, "label_id": 0, "z_order": 0, "bbox": [1759.19, 720.4, 66.80999999999995, 111.70000000000005]}, {"id": 0, "type": "bbox", "attributes": {"occluded": false, "rotation": 0.0, "track_id": 4, "keyframe": true}, "group": 0, "label_id": 0, "z_order": 0, "bbox": [1209.68, 1123.33, 55.01999999999998, 25.87000000000012]}], "attr": {"frame": 50}}, {"id": "SORXX/125830/SORKM_125830_2021Y11M15D_17H14M48S_img", "annotations": [{"id": 0, "type": "bbox", "attributes": {"occluded": false, "rotation": 0.0, "track_id": 0, "keyframe": true}, "group": 0, "label_id": 0, "z_order": 0, "bbox": [522.01, 1403.67, 427.49, 142.12999999999988]}, {"id": 0, "type": "bbox", "attributes": {"occluded": false, "rotation": 0.0, "track_id": 1, "keyframe": true}, "group": 0, "label_id": 0, "z_order": 0, "bbox": [588.01, 766.8, 43.690000000000055, 42.33000000000004]}, {"id": 0, "type": "bbox", "attributes": {"occluded": false, "rotation": 0.0, "track_id": 2, "keyframe": true}, "group": 0, "label_id": 0, "z_order": 0, "bbox": [1664.1, 1058.0, 177.30000000000018, 456.3699999999999]}, {"id": 0, "type": "bbox", "attributes": {"occluded": false, "rotation": 0.0, "track_id": 3, "keyframe": true}, "group": 0, "label_id": 0, "z_order": 0, "bbox": [1755.57, 717.99, 70.93000000000006, 110.00999999999999]}, {"id": 0, "type": "bbox", "attributes": {"occluded": false, "rotation": 0.0, "track_id": 4, "keyframe": true}, "group": 0, "label_id": 0, "z_order": 0, "bbox": [1208.41, 1122.07, 54.08999999999992, 24.930000000000064]}], "attr": {"frame": 51}}, {"id": "SORXX/125830/SORKM_125830_2021Y11M16D_00H47M10S_img", "annotations": [{"id": 0, "type": "bbox", "attributes": {"occluded": false, "rotation": 0.0, "track_id": 0, "keyframe": true}, "group": 0, "label_id": 0, "z_order": 0, "bbox": [521.15, 1410.59, 435.25, 136.11000000000013]}, {"id": 0, "type": "bbox", "attributes": {"occluded": false, "rotation": 0.0, "track_id": 1, "keyframe": true}, "group": 0, "label_id": 0, "z_order": 0, "bbox": [589.36, 773.7, 44.34000000000003, 43.479999999999905]}, {"id": 0, "type": "bbox", "attributes": {"occluded": false, "rotation": 0.0, "track_id": 2, "keyframe": true}, "group": 0, "label_id": 0, "z_order": 0, "bbox": [1676.1, 1063.0, 172.80000000000018, 451.3699999999999]}, {"id": 0, "type": "bbox", "attributes": {"occluded": false, "rotation": 0.0, "track_id": 3, "keyframe": true}, "group": 0, "label_id": 0, "z_order": 0, "bbox": [1754.12, 722.09, 74.2800000000002, 112.90999999999997]}, {"id": 0, "type": "bbox", "attributes": {"occluded": false, "rotation": 0.0, "track_id": 4, "keyframe": true}, "group": 0, "label_id": 0, "z_order": 0, "bbox": [1208.96, 1129.57, 55.039999999999964, 25.330000000000155]}], "attr": {"frame": 52}}, {"id": "SORXX/125830/SORKM_125830_2021Y11M16D_08H39M55S_img", "annotations": [{"id": 0, "type": "bbox", "attributes": {"occluded": false, "rotation": 0.0, "track_id": 0, "keyframe": true}, "group": 0, "label_id": 0, "z_order": 0, "bbox": [518.55, 1412.32, 439.55000000000007, 136.98000000000002]}, {"id": 0, "type": "bbox", "attributes": {"occluded": false, "rotation": 0.0, "track_id": 1, "keyframe": true}, "group": 0, "label_id": 0, "z_order": 0, "bbox": [584.83, 776.9, 43.469999999999914, 41.120000000000005]}, {"id": 0, "type": "bbox", "attributes": {"occluded": false, "rotation": 0.0, "track_id": 2, "keyframe": true}, "group": 0, "label_id": 0, "z_order": 0, "bbox": [1685.1, 1066.5, 177.80000000000018, 447.8699999999999]}, {"id": 0, "type": "bbox", "attributes": {"occluded": false, "rotation": 0.0, "track_id": 3, "keyframe": true}, "group": 0, "label_id": 0, "z_order": 0, "bbox": [1742.78, 719.19, 78.12000000000012, 117.50999999999999]}, {"id": 0, "type": "bbox", "attributes": {"occluded": false, "rotation": 0.0, "track_id": 4, "keyframe": true}, "group": 0, "label_id": 0, "z_order": 0, "bbox": [1204.75, 1130.85, 53.34999999999991, 26.75]}], "attr": {"frame": 53}}, {"id": "SORXX/125830/SORKM_125830_2021Y11M16D_12H45M41S_img", "annotations": [{"id": 0, "type": "bbox", "attributes": {"occluded": false, "rotation": 0.0, "track_id": 0, "keyframe": true}, "group": 0, "label_id": 0, "z_order": 0, "bbox": [522.7, 1410.24, 442.69999999999993, 126.55999999999995]}, {"id": 0, "type": "bbox", "attributes": {"occluded": false, "rotation": 0.0, "track_id": 1, "keyframe": true}, "group": 0, "label_id": 0, "z_order": 0, "bbox": [589.86, 769.9, 42.34000000000003, 42.42000000000007]}, {"id": 0, "type": "bbox", "attributes": {"occluded": false, "rotation": 0.0, "track_id": 2, "keyframe": true}, "group": 0, "label_id": 0, "z_order": 0, "bbox": [1690.1, 1052.5, 186.80000000000018, 461.8699999999999]}, {"id": 0, "type": "bbox", "attributes": {"occluded": false, "rotation": 0.0, "track_id": 3, "keyframe": true}, "group": 0, "label_id": 0, "z_order": 0, "bbox": [1742.29, 707.6, 88.71000000000004, 119.19999999999993]}, {"id": 0, "type": "bbox", "attributes": {"occluded": false, "rotation": 0.0, "track_id": 4, "keyframe": true}, "group": 0, "label_id": 0, "z_order": 0, "bbox": [1209.14, 1125.0, 52.75999999999999, 26.200000000000045]}], "attr": {"frame": 54}}, {"id": "SORXX/125830/SORKM_125830_2021Y11M16D_16H39M31S_img", "annotations": [{"id": 0, "type": "bbox", "attributes": {"occluded": false, "rotation": 0.0, "track_id": 0, "keyframe": false}, "group": 0, "label_id": 0, "z_order": 0, "bbox": [522.7, 1410.24, 443.19999999999993, 125.00999999999999]}, {"id": 0, "type": "bbox", "attributes": {"occluded": false, "rotation": 0.0, "track_id": 1, "keyframe": true}, "group": 0, "label_id": 0, "z_order": 0, "bbox": [589.86, 770.4, 44.84000000000003, 43.930000000000064]}, {"id": 0, "type": "bbox", "attributes": {"occluded": false, "rotation": 0.0, "track_id": 2, "keyframe": true}, "group": 0, "label_id": 0, "z_order": 0, "bbox": [1684.6, 1054.5, 185.30000000000018, 459.8699999999999]}, {"id": 0, "type": "bbox", "attributes": {"occluded": false, "rotation": 0.0, "track_id": 3, "keyframe": true}, "group": 0, "label_id": 0, "z_order": 0, "bbox": [1742.54, 706.4, 87.96000000000004, 122.60000000000002]}, {"id": 0, "type": "bbox", "attributes": {"occluded": false, "rotation": 0.0, "track_id": 4, "keyframe": true}, "group": 0, "label_id": 0, "z_order": 0, "bbox": [1211.34, 1126.09, 52.06000000000017, 27.810000000000173]}], "attr": {"frame": 55}}, {"id": "SORXX/125830/SORKM_125830_2021Y11M17D_01H29M19S_img", "annotations": [{"id": 0, "type": "bbox", "attributes": {"occluded": false, "rotation": 0.0, "track_id": 0, "keyframe": true}, "group": 0, "label_id": 0, "z_order": 0, "bbox": [522.7, 1410.24, 443.69999999999993, 123.46000000000004]}, {"id": 0, "type": "bbox", "attributes": {"occluded": false, "rotation": 0.0, "track_id": 1, "keyframe": true}, "group": 0, "label_id": 0, "z_order": 0, "bbox": [586.84, 771.9, 44.360000000000014, 41.42000000000007]}, {"id": 0, "type": "bbox", "attributes": {"occluded": false, "rotation": 0.0, "track_id": 2, "keyframe": true}, "group": 0, "label_id": 0, "z_order": 0, "bbox": [1682.1, 1049.5, 194.80000000000018, 464.8699999999999]}, {"id": 0, "type": "bbox", "attributes": {"occluded": false, "rotation": 0.0, "track_id": 3, "keyframe": true}, "group": 0, "label_id": 0, "z_order": 0, "bbox": [1735.29, 698.19, 89.61000000000013, 128.1099999999999]}, {"id": 0, "type": "bbox", "attributes": {"occluded": false, "rotation": 0.0, "track_id": 4, "keyframe": true}, "group": 0, "label_id": 0, "z_order": 0, "bbox": [1210.07, 1126.22, 50.13000000000011, 27.779999999999973]}], "attr": {"frame": 56}}, {"id": "SORXX/125830/SORKM_125830_2021Y11M17D_08H13M26S_img", "annotations": [{"id": 0, "type": "bbox", "attributes": {"occluded": false, "rotation": 0.0, "track_id": 0, "keyframe": true}, "group": 0, "label_id": 0, "z_order": 0, "bbox": [514.4, 1417.51, 456.20000000000005, 119.28999999999996]}, {"id": 0, "type": "bbox", "attributes": {"occluded": false, "rotation": 0.0, "track_id": 1, "keyframe": true}, "group": 0, "label_id": 0, "z_order": 0, "bbox": [585.16, 779.1, 42.04000000000008, 40.92999999999995]}, {"id": 0, "type": "bbox", "attributes": {"occluded": false, "rotation": 0.0, "track_id": 2, "keyframe": true}, "group": 0, "label_id": 0, "z_order": 0, "bbox": [1681.1, 1057.0, 201.30000000000018, 457.3699999999999]}, {"id": 0, "type": "bbox", "attributes": {"occluded": false, "rotation": 0.0, "track_id": 3, "keyframe": true}, "group": 0, "label_id": 0, "z_order": 0, "bbox": [1725.64, 702.29, 94.45999999999981, 130.31000000000006]}, {"id": 0, "type": "bbox", "attributes": {"occluded": false, "rotation": 0.0, "track_id": 4, "keyframe": true}, "group": 0, "label_id": 0, "z_order": 0, "bbox": [1207.02, 1132.83, 48.180000000000064, 28.670000000000073]}], "attr": {"frame": 57}}, {"id": "SORXX/125830/SORKM_125830_2021Y11M17D_12H13M14S_img", "annotations": [{"id": 0, "type": "bbox", "attributes": {"occluded": false, "rotation": 0.0, "track_id": 0, "keyframe": true}, "group": 0, "label_id": 0, "z_order": 0, "bbox": [516.47, 1412.32, 456.23, 115.18000000000006]}, {"id": 0, "type": "bbox", "attributes": {"occluded": false, "rotation": 0.0, "track_id": 1, "keyframe": true}, "group": 0, "label_id": 0, "z_order": 0, "bbox": [589.69, 768.4, 41.90999999999997, 42.40999999999997]}, {"id": 0, "type": "bbox", "attributes": {"occluded": false, "rotation": 0.0, "track_id": 2, "keyframe": true}, "group": 0, "label_id": 0, "z_order": 0, "bbox": [1688.6, 1051.5, 212.30000000000018, 462.8699999999999]}, {"id": 0, "type": "bbox", "attributes": {"occluded": false, "rotation": 0.0, "track_id": 3, "keyframe": true}, "group": 0, "label_id": 0, "z_order": 0, "bbox": [1725.39, 690.94, 101.50999999999999, 129.8599999999999]}, {"id": 0, "type": "bbox", "attributes": {"occluded": false, "rotation": 0.0, "track_id": 4, "keyframe": true}, "group": 0, "label_id": 0, "z_order": 0, "bbox": [1211.98, 1122.41, 47.42000000000007, 29.189999999999827]}], "attr": {"frame": 58}}, {"id": "SORXX/125830/SORKM_125830_2021Y11M17D_16H13M14S_img", "annotations": [{"id": 0, "type": "bbox", "attributes": {"occluded": false, "rotation": 0.0, "track_id": 0, "keyframe": true}, "group": 0, "label_id": 0, "z_order": 0, "bbox": [515.44, 1413.36, 453.05999999999995, 116.24000000000001]}, {"id": 0, "type": "bbox", "attributes": {"occluded": false, "rotation": 0.0, "track_id": 1, "keyframe": true}, "group": 0, "label_id": 0, "z_order": 0, "bbox": [589.69, 770.6, 41.1099999999999, 43.059999999999945]}, {"id": 0, "type": "bbox", "attributes": {"occluded": false, "rotation": 0.0, "track_id": 2, "keyframe": true}, "group": 0, "label_id": 0, "z_order": 0, "bbox": [1685.1, 1049.5, 202.30000000000018, 464.8699999999999]}, {"id": 0, "type": "bbox", "attributes": {"occluded": false, "rotation": 0.0, "track_id": 3, "keyframe": true}, "group": 0, "label_id": 0, "z_order": 0, "bbox": [1722.74, 693.36, 105.55999999999995, 130.53999999999996]}, {"id": 0, "type": "bbox", "attributes": {"occluded": false, "rotation": 0.0, "track_id": 4, "keyframe": true}, "group": 0, "label_id": 0, "z_order": 0, "bbox": [1212.1, 1125.97, 47.430000000000064, 29.190000000000055]}], "attr": {"frame": 59}}, {"id": "SORXX/125830/SORKM_125830_2021Y11M18D_13H48M34S_img", "annotations": [{"id": 0, "type": "bbox", "attributes": {"occluded": false, "rotation": 0.0, "track_id": 0, "keyframe": true}, "group": 0, "label_id": 0, "z_order": 0, "bbox": [520.63, 1415.43, 458.27, 117.26999999999998]}, {"id": 0, "type": "bbox", "attributes": {"occluded": false, "rotation": 0.0, "track_id": 1, "keyframe": true}, "group": 0, "label_id": 0, "z_order": 0, "bbox": [590.19, 773.1, 41.809999999999945, 42.069999999999936]}, {"id": 0, "type": "bbox", "attributes": {"occluded": false, "rotation": 0.0, "track_id": 2, "keyframe": true}, "group": 0, "label_id": 0, "z_order": 0, "bbox": [1683.6, 1044.5, 207.30000000000018, 469.8699999999999]}, {"id": 0, "type": "bbox", "attributes": {"occluded": false, "rotation": 0.0, "track_id": 3, "keyframe": true}, "group": 0, "label_id": 0, "z_order": 0, "bbox": [1704.63, 673.32, 118.86999999999989, 150.57999999999993]}], "attr": {"frame": 60}}, {"id": "SORXX/125830/SORKM_125830_2021Y11M18D_17H34M26S_img", "annotations": [{"id": 0, "type": "bbox", "attributes": {"occluded": false, "rotation": 0.0, "track_id": 0, "keyframe": true}, "group": 0, "label_id": 0, "z_order": 0, "bbox": [520.63, 1411.28, 453.07000000000005, 115.22000000000003]}, {"id": 0, "type": "bbox", "attributes": {"occluded": false, "rotation": 0.0, "track_id": 1, "keyframe": true}, "group": 0, "label_id": 0, "z_order": 0, "bbox": [590.86, 768.7, 42.139999999999986, 43.94999999999993]}, {"id": 0, "type": "bbox", "attributes": {"occluded": false, "rotation": 0.0, "track_id": 2, "keyframe": true}, "group": 0, "label_id": 0, "z_order": 0, "bbox": [1682.1, 1038.0, 196.80000000000018, 476.3699999999999]}, {"id": 0, "type": "bbox", "attributes": {"occluded": false, "rotation": 0.0, "track_id": 3, "keyframe": true}, "group": 0, "label_id": 0, "z_order": 0, "bbox": [1702.22, 667.28, 124.18000000000006, 153.22000000000003]}], "attr": {"frame": 61}}, {"id": "SORXX/125830/SORKM_125830_2021Y11M19D_00H51M40S_img", "annotations": [{"id": 0, "type": "bbox", "attributes": {"occluded": false, "rotation": 0.0, "track_id": 0, "keyframe": true}, "group": 0, "label_id": 0, "z_order": 0, "bbox": [519.59, 1417.51, 456.2099999999999, 115.19000000000005]}, {"id": 0, "type": "bbox", "attributes": {"occluded": false, "rotation": 0.0, "track_id": 1, "keyframe": true}, "group": 0, "label_id": 0, "z_order": 0, "bbox": [590.19, 775.6, 40.809999999999945, 42.57999999999993]}, {"id": 0, "type": "bbox", "attributes": {"occluded": false, "rotation": 0.0, "track_id": 2, "keyframe": true}, "group": 0, "label_id": 0, "z_order": 0, "bbox": [1667.1, 1045.0, 194.80000000000018, 475.9000000000001]}, {"id": 0, "type": "bbox", "attributes": {"occluded": false, "rotation": 0.0, "track_id": 3, "keyframe": true}, "group": 0, "label_id": 0, "z_order": 0, "bbox": [1691.59, 671.39, 128.31000000000017, 155.90999999999997]}], "attr": {"frame": 62}}, {"id": "SORXX/125830/SORKM_125830_2021Y11M19D_09H30M49S_img", "annotations": [{"id": 0, "type": "bbox", "attributes": {"occluded": false, "rotation": 0.0, "track_id": 0, "keyframe": true}, "group": 0, "label_id": 0, "z_order": 0, "bbox": [520.63, 1411.28, 459.37, 115.22000000000003]}, {"id": 0, "type": "bbox", "attributes": {"occluded": false, "rotation": 0.0, "track_id": 1, "keyframe": true}, "group": 0, "label_id": 0, "z_order": 0, "bbox": [590.53, 769.2, 40.47000000000003, 42.27999999999997]}, {"id": 0, "type": "bbox", "attributes": {"occluded": false, "rotation": 0.0, "track_id": 2, "keyframe": true}, "group": 0, "label_id": 0, "z_order": 0, "bbox": [1664.1, 1040.5, 192.30000000000018, 475.9000000000001]}, {"id": 0, "type": "bbox", "attributes": {"occluded": false, "rotation": 0.0, "track_id": 3, "keyframe": true}, "group": 0, "label_id": 0, "z_order": 0, "bbox": [1680.73, 658.83, 139.3699999999999, 160.26999999999998]}], "attr": {"frame": 63}}, {"id": "SORXX/125830/SORKM_125830_2021Y11M19D_13H28M33S_img", "annotations": [{"id": 0, "type": "bbox", "attributes": {"occluded": false, "rotation": 0.0, "track_id": 0, "keyframe": true}, "group": 0, "label_id": 0, "z_order": 0, "bbox": [510.25, 1406.09, 466.65, 101.71000000000004]}, {"id": 0, "type": "bbox", "attributes": {"occluded": false, "rotation": 0.0, "track_id": 1, "keyframe": true}, "group": 0, "label_id": 0, "z_order": 0, "bbox": [581.31, 761.7, 41.79000000000008, 44.40999999999997]}, {"id": 0, "type": "bbox", "attributes": {"occluded": false, "rotation": 0.0, "track_id": 2, "keyframe": true}, "group": 0, "label_id": 0, "z_order": 0, "bbox": [1656.1, 1035.0, 188.30000000000018, 479.4000000000001]}, {"id": 0, "type": "bbox", "attributes": {"occluded": false, "rotation": 0.0, "track_id": 3, "keyframe": true}, "group": 0, "label_id": 0, "z_order": 0, "bbox": [1662.86, 651.44, 154.1400000000001, 162.26]}], "attr": {"frame": 64}}, {"id": "SORXX/125830/SORKM_125830_2021Y11M20D_01H34M57S_img", "annotations": [{"id": 0, "type": "bbox", "attributes": {"occluded": false, "rotation": 0.0, "track_id": 0, "keyframe": true}, "group": 0, "label_id": 0, "z_order": 0, "bbox": [518.55, 1409.21, 469.75, 101.69000000000005]}, {"id": 0, "type": "bbox", "attributes": {"occluded": false, "rotation": 0.0, "track_id": 1, "keyframe": true}, "group": 0, "label_id": 0, "z_order": 0, "bbox": [590.02, 771.8, 40.77999999999997, 43.030000000000086]}, {"id": 0, "type": "bbox", "attributes": {"occluded": false, "rotation": 0.0, "track_id": 2, "keyframe": true}, "group": 0, "label_id": 0, "z_order": 0, "bbox": [1663.1, 1028.0, 168.80000000000018, 492.4000000000001]}, {"id": 0, "type": "bbox", "attributes": {"occluded": false, "rotation": 0.0, "track_id": 3, "keyframe": true}, "group": 0, "label_id": 0, "z_order": 0, "bbox": [1664.31, 651.15, 157.59000000000015, 168.95000000000005]}], "attr": {"frame": 65}}, {"id": "SORXX/125830/SORKM_125830_2021Y11M20D_13H02M56S_img", "annotations": [{"id": 0, "type": "bbox", "attributes": {"occluded": false, "rotation": 0.0, "track_id": 0, "keyframe": true}, "group": 0, "label_id": 0, "z_order": 0, "bbox": [523.74, 1401.94, 457.26, 99.65999999999985]}, {"id": 0, "type": "bbox", "attributes": {"occluded": false, "rotation": 0.0, "track_id": 1, "keyframe": true}, "group": 0, "label_id": 0, "z_order": 0, "bbox": [591.37, 765.8, 39.92999999999995, 43.33000000000004]}, {"id": 0, "type": "bbox", "attributes": {"occluded": false, "rotation": 0.0, "track_id": 2, "keyframe": true}, "group": 0, "label_id": 0, "z_order": 0, "bbox": [1660.6, 1016.5, 140.30000000000018, 500.4000000000001]}, {"id": 0, "type": "bbox", "attributes": {"occluded": false, "rotation": 0.0, "track_id": 3, "keyframe": true}, "group": 0, "label_id": 0, "z_order": 0, "bbox": [1646.93, 647.1, 176.16999999999985, 169.19999999999993]}], "attr": {"frame": 66}}, {"id": "SORXX/125830/SORKM_125830_2021Y11M21D_00H29M41S_img", "annotations": [{"id": 0, "type": "bbox", "attributes": {"occluded": false, "rotation": 0.0, "track_id": 0, "keyframe": true}, "group": 0, "label_id": 0, "z_order": 0, "bbox": [523.74, 1402.98, 463.46000000000004, 100.72000000000003]}, {"id": 0, "type": "bbox", "attributes": {"occluded": false, "rotation": 0.0, "track_id": 1, "keyframe": true}, "group": 0, "label_id": 0, "z_order": 0, "bbox": [591.7, 775.9, 39.799999999999955, 42.79000000000008]}, {"id": 0, "type": "bbox", "attributes": {"occluded": false, "rotation": 0.0, "track_id": 2, "keyframe": true}, "group": 0, "label_id": 0, "z_order": 0, "bbox": [1662.8, 1017.9, 138.10000000000014, 512.0000000000001]}, {"id": 0, "type": "bbox", "attributes": {"occluded": false, "rotation": 0.0, "track_id": 3, "keyframe": true}, "group": 0, "label_id": 0, "z_order": 0, "bbox": [1635.66, 662.53, 187.03999999999996, 160.87]}], "attr": {"frame": 67}}, {"id": "SORXX/125830/SORKM_125830_2021Y11M21D_12H29M25S_img", "annotations": [{"id": 0, "type": "bbox", "attributes": {"occluded": false, "rotation": 0.0, "track_id": 0, "keyframe": true}, "group": 0, "label_id": 0, "z_order": 0, "bbox": [524.78, 1402.98, 463.46000000000004, 100.72000000000003]}, {"id": 0, "type": "bbox", "attributes": {"occluded": false, "rotation": 0.0, "track_id": 1, "keyframe": true}, "group": 0, "label_id": 0, "z_order": 0, "bbox": [592.2, 775.2, 40.0, 40.469999999999914]}, {"id": 0, "type": "bbox", "attributes": {"occluded": false, "rotation": 0.0, "track_id": 2, "keyframe": true}, "group": 0, "label_id": 0, "z_order": 0, "bbox": [1664.2, 1017.9, 136.70000000000005, 518.5000000000001]}, {"id": 0, "type": "bbox", "attributes": {"occluded": false, "rotation": 0.0, "track_id": 3, "keyframe": true}, "group": 0, "label_id": 0, "z_order": 0, "bbox": [1627.32, 663.79, 196.18000000000006, 155.01]}], "attr": {"frame": 68}}, {"id": "SORXX/125830/SORKM_125830_2021Y11M21D_16H29M20S_img", "annotations": [{"id": 0, "type": "bbox", "attributes": {"occluded": false, "rotation": 0.0, "track_id": 0, "keyframe": true}, "group": 0, "label_id": 0, "z_order": 0, "bbox": [527.89, 1397.79, 458.31000000000006, 99.71000000000004]}, {"id": 0, "type": "bbox", "attributes": {"occluded": false, "rotation": 0.0, "track_id": 1, "keyframe": true}, "group": 0, "label_id": 0, "z_order": 0, "bbox": [593.04, 769.8, 39.16000000000008, 42.00999999999999]}, {"id": 0, "type": "bbox", "attributes": {"occluded": false, "rotation": 0.0, "track_id": 2, "keyframe": true}, "group": 0, "label_id": 0, "z_order": 0, "bbox": [1657.7, 1017.9, 143.20000000000005, 514.1999999999999]}, {"id": 0, "type": "bbox", "attributes": {"occluded": false, "rotation": 0.0, "track_id": 3, "keyframe": true}, "group": 0, "label_id": 0, "z_order": 0, "bbox": [1624.4, 658.36, 199.0999999999999, 159.14]}], "attr": {"frame": 69}}, {"id": "SORXX/125830/SORKM_125830_2021Y11M22D_01H11M16S_img", "annotations": [{"id": 0, "type": "bbox", "attributes": {"occluded": false, "rotation": 0.0, "track_id": 0, "keyframe": true}, "group": 0, "label_id": 0, "z_order": 0, "bbox": [522.7, 1399.9, 472.79999999999995, 98.63999999999987]}, {"id": 0, "type": "bbox", "attributes": {"occluded": false, "rotation": 0.0, "track_id": 1, "keyframe": true}, "group": 0, "label_id": 0, "z_order": 0, "bbox": [588.85, 773.3, 41.64999999999998, 40.020000000000095]}, {"id": 0, "type": "bbox", "attributes": {"occluded": false, "rotation": 0.0, "track_id": 2, "keyframe": true}, "group": 0, "label_id": 0, "z_order": 0, "bbox": [1664.2, 1017.9, 136.70000000000005, 520.0000000000001]}, {"id": 0, "type": "bbox", "attributes": {"occluded": false, "rotation": 0.0, "track_id": 3, "keyframe": true}, "group": 0, "label_id": 0, "z_order": 0, "bbox": [1617.73, 664.62, 204.97000000000003, 154.17999999999995]}], "attr": {"frame": 70}}, {"id": "SORXX/125830/SORKM_125830_2021Y11M22D_14H41M51S_img", "annotations": [{"id": 0, "type": "bbox", "attributes": {"occluded": false, "rotation": 0.0, "track_id": 0, "keyframe": true}, "group": 0, "label_id": 0, "z_order": 0, "bbox": [524.78, 1392.6, 468.62, 102.82000000000016]}, {"id": 0, "type": "bbox", "attributes": {"occluded": false, "rotation": 0.0, "track_id": 1, "keyframe": true}, "group": 0, "label_id": 0, "z_order": 0, "bbox": [588.68, 769.3, 41.020000000000095, 41.50999999999999]}, {"id": 0, "type": "bbox", "attributes": {"occluded": false, "rotation": 0.0, "track_id": 2, "keyframe": true}, "group": 0, "label_id": 0, "z_order": 0, "bbox": [1666.4, 1014.3, 134.5, 525.8]}, {"id": 0, "type": "bbox", "attributes": {"occluded": false, "rotation": 0.0, "track_id": 3, "keyframe": true}, "group": 0, "label_id": 0, "z_order": 0, "bbox": [1600.62, 672.13, 217.98000000000002, 139.57000000000005]}], "attr": {"frame": 71}}, {"id": "SORXX/125830/SORKM_125830_2021Y11M22D_18H24M33S_img", "annotations": [{"id": 0, "type": "bbox", "attributes": {"occluded": false, "rotation": 0.0, "track_id": 0, "keyframe": true}, "group": 0, "label_id": 0, "z_order": 0, "bbox": [524.78, 1393.6, 468.62, 102.86000000000013]}, {"id": 0, "type": "bbox", "attributes": {"occluded": false, "rotation": 0.0, "track_id": 1, "keyframe": true}, "group": 0, "label_id": 0, "z_order": 0, "bbox": [588.01, 771.3, 39.49000000000001, 40.50999999999999]}, {"id": 0, "type": "bbox", "attributes": {"occluded": false, "rotation": 0.0, "track_id": 2, "keyframe": true}, "group": 0, "label_id": 0, "z_order": 0, "bbox": [1664.6, 1014.3, 136.30000000000018, 528.8]}, {"id": 0, "type": "bbox", "attributes": {"occluded": false, "rotation": 0.0, "track_id": 3, "keyframe": true}, "group": 0, "label_id": 0, "z_order": 0, "bbox": [1600.62, 672.13, 221.7800000000002, 141.66999999999996]}], "attr": {"frame": 72}}, {"id": "SORXX/125830/SORKM_125830_2021Y11M23D_00H02M57S_img", "annotations": [{"id": 0, "type": "bbox", "attributes": {"occluded": false, "rotation": 0.0, "track_id": 0, "keyframe": true}, "group": 0, "label_id": 0, "z_order": 0, "bbox": [523.7, 1398.8, 469.69999999999993, 99.70000000000005]}, {"id": 0, "type": "bbox", "attributes": {"occluded": false, "rotation": 0.0, "track_id": 1, "keyframe": true}, "group": 0, "label_id": 0, "z_order": 0, "bbox": [590.19, 781.7, 39.00999999999999, 41.51999999999998]}, {"id": 0, "type": "bbox", "attributes": {"occluded": false, "rotation": 0.0, "track_id": 2, "keyframe": true}, "group": 0, "label_id": 0, "z_order": 0, "bbox": [1670.6, 1023.9, 130.30000000000018, 529.4]}, {"id": 0, "type": "bbox", "attributes": {"occluded": false, "rotation": 0.0, "track_id": 3, "keyframe": true}, "group": 0, "label_id": 0, "z_order": 0, "bbox": [1595.2, 680.0, 227.5999999999999, 142.10000000000002]}], "attr": {"frame": 73}}, {"id": "SORXX/125830/SORKM_125830_2021Y11M23D_09H16M32S_img", "annotations": [{"id": 0, "type": "bbox", "attributes": {"occluded": false, "rotation": 0.0, "track_id": 0, "keyframe": true}, "group": 0, "label_id": 0, "z_order": 0, "bbox": [523.7, 1386.3, 471.79999999999995, 108.0]}, {"id": 0, "type": "bbox", "attributes": {"occluded": false, "rotation": 0.0, "track_id": 1, "keyframe": true}, "group": 0, "label_id": 0, "z_order": 0, "bbox": [591.03, 774.7, 38.870000000000005, 40.299999999999955]}, {"id": 0, "type": "bbox", "attributes": {"occluded": false, "rotation": 0.0, "track_id": 2, "keyframe": true}, "group": 0, "label_id": 0, "z_order": 0, "bbox": [1670.0, 1025.1, 130.9000000000001, 525.8000000000002]}, {"id": 0, "type": "bbox", "attributes": {"occluded": false, "rotation": 0.0, "track_id": 3, "keyframe": true}, "group": 0, "label_id": 0, "z_order": 0, "bbox": [1595.2, 679.2, 227.20000000000005, 136.5999999999999]}], "attr": {"frame": 74}}, {"id": "SORXX/125830/SORKM_125830_2021Y11M23D_13H06M33S_img", "annotations": [{"id": 0, "type": "bbox", "attributes": {"occluded": false, "rotation": 0.0, "track_id": 0, "keyframe": true}, "group": 0, "label_id": 0, "z_order": 0, "bbox": [523.7, 1371.8, 472.79999999999995, 122.5]}, {"id": 0, "type": "bbox", "attributes": {"occluded": false, "rotation": 0.0, "track_id": 1, "keyframe": true}, "group": 0, "label_id": 0, "z_order": 0, "bbox": [590.86, 768.7, 38.539999999999964, 38.91999999999996]}, {"id": 0, "type": "bbox", "attributes": {"occluded": false, "rotation": 0.0, "track_id": 2, "keyframe": true}, "group": 0, "label_id": 0, "z_order": 0, "bbox": [1668.2, 1016.7, 139.29999999999995, 528.2]}, {"id": 0, "type": "bbox", "attributes": {"occluded": false, "rotation": 0.0, "track_id": 3, "keyframe": true}, "group": 0, "label_id": 0, "z_order": 0, "bbox": [1592.7, 675.4, 229.29999999999995, 133.70000000000005]}], "attr": {"frame": 75}}, {"id": "SORXX/125830/SORKM_125830_2021Y11M23D_17H07M02S_img", "annotations": [{"id": 0, "type": "bbox", "attributes": {"occluded": false, "rotation": 0.0, "track_id": 0, "keyframe": true}, "group": 0, "label_id": 0, "z_order": 0, "bbox": [523.7, 1376.0, 473.79999999999995, 113.09999999999991]}, {"id": 0, "type": "bbox", "attributes": {"occluded": false, "rotation": 0.0, "track_id": 1, "keyframe": true}, "group": 0, "label_id": 0, "z_order": 0, "bbox": [587.34, 774.6, 38.15999999999997, 38.559999999999945]}, {"id": 0, "type": "bbox", "attributes": {"occluded": false, "rotation": 0.0, "track_id": 2, "keyframe": true}, "group": 0, "label_id": 0, "z_order": 0, "bbox": [1665.8, 1016.7, 141.70000000000005, 535.3999999999999]}, {"id": 0, "type": "bbox", "attributes": {"occluded": false, "rotation": 0.0, "track_id": 3, "keyframe": true}, "group": 0, "label_id": 0, "z_order": 0, "bbox": [1586.4, 677.9, 233.0999999999999, 137.0]}], "attr": {"frame": 76}}, {"id": "SORXX/125830/SORKM_125830_2021Y11M24D_00H48M55S_img", "annotations": [{"id": 0, "type": "bbox", "attributes": {"occluded": false, "rotation": 0.0, "track_id": 0, "keyframe": false}, "group": 0, "label_id": 0, "z_order": 0, "bbox": [523.7, 1373.4, 473.29999999999995, 123.5]}, {"id": 0, "type": "bbox", "attributes": {"occluded": false, "rotation": 0.0, "track_id": 1, "keyframe": true}, "group": 0, "label_id": 0, "z_order": 0, "bbox": [589.35, 781.3, 37.64999999999998, 39.23000000000002]}, {"id": 0, "type": "bbox", "attributes": {"occluded": false, "rotation": 0.0, "track_id": 2, "keyframe": true}, "group": 0, "label_id": 0, "z_order": 0, "bbox": [1667.6, 1020.9, 139.30000000000018, 539.6]}, {"id": 0, "type": "bbox", "attributes": {"occluded": false, "rotation": 0.0, "track_id": 3, "keyframe": true}, "group": 0, "label_id": 0, "z_order": 0, "bbox": [1586.0, 687.5, 233.9000000000001, 132.0]}], "attr": {"frame": 77}}, {"id": "SORXX/125830/SORKM_125830_2021Y11M24D_08H41M32S_img", "annotations": [{"id": 0, "type": "bbox", "attributes": {"occluded": false, "rotation": 0.0, "track_id": 0, "keyframe": true}, "group": 0, "label_id": 0, "z_order": 0, "bbox": [523.7, 1370.8, 472.79999999999995, 133.9000000000001]}, {"id": 0, "type": "bbox", "attributes": {"occluded": false, "rotation": 0.0, "track_id": 1, "keyframe": true}, "group": 0, "label_id": 0, "z_order": 0, "bbox": [589.69, 783.5, 37.809999999999945, 38.039999999999964]}, {"id": 0, "type": "bbox", "attributes": {"occluded": false, "rotation": 0.0, "track_id": 2, "keyframe": true}, "group": 0, "label_id": 0, "z_order": 0, "bbox": [1643.0, 1035.9, 161.5, 524.5999999999999]}, {"id": 0, "type": "bbox", "attributes": {"occluded": false, "rotation": 0.0, "track_id": 3, "keyframe": true}, "group": 0, "label_id": 0, "z_order": 0, "bbox": [1584.7, 690.4, 235.5999999999999, 132.39999999999998]}], "attr": {"frame": 78}}, {"id": "SORXX/125830/SORKM_125830_2021Y11M24D_12H41M03S_img", "annotations": [{"id": 0, "type": "bbox", "attributes": {"occluded": false, "rotation": 0.0, "track_id": 0, "keyframe": true}, "group": 0, "label_id": 0, "z_order": 0, "bbox": [523.7, 1348.0, 473.79999999999995, 156.70000000000005]}, {"id": 0, "type": "bbox", "attributes": {"occluded": false, "rotation": 0.0, "track_id": 1, "keyframe": true}, "group": 0, "label_id": 0, "z_order": 0, "bbox": [589.85, 776.5, 38.64999999999998, 38.15999999999997]}, {"id": 0, "type": "bbox", "attributes": {"occluded": false, "rotation": 0.0, "track_id": 2, "keyframe": true}, "group": 0, "label_id": 0, "z_order": 0, "bbox": [1626.8, 1026.3, 172.29999999999995, 534.2]}, {"id": 0, "type": "bbox", "attributes": {"occluded": false, "rotation": 0.0, "track_id": 3, "keyframe": true}, "group": 0, "label_id": 0, "z_order": 0, "bbox": [1583.4, 678.3, 237.29999999999995, 134.5]}], "attr": {"frame": 79}}, {"id": "SORXX/125830/SORKM_125830_2021Y11M24D_16H41M09S_img", "annotations": [{"id": 0, "type": "bbox", "attributes": {"occluded": false, "rotation": 0.0, "track_id": 0, "keyframe": true}, "group": 0, "label_id": 0, "z_order": 0, "bbox": [523.7, 1336.6, 473.79999999999995, 150.5]}, {"id": 0, "type": "bbox", "attributes": {"occluded": false, "rotation": 0.0, "track_id": 1, "keyframe": true}, "group": 0, "label_id": 0, "z_order": 0, "bbox": [590.52, 777.8, 38.27999999999997, 38.54000000000008]}, {"id": 0, "type": "bbox", "attributes": {"occluded": false, "rotation": 0.0, "track_id": 3, "keyframe": true}, "group": 0, "label_id": 0, "z_order": 0, "bbox": [1583.0, 680.0, 235.20000000000005, 137.0]}, {"id": 0, "type": "bbox", "attributes": {"occluded": false, "rotation": 0.0, "track_id": 2, "keyframe": true}, "group": 0, "label_id": 0, "z_order": 1, "bbox": [1617.8, 1030.5, 181.29999999999995, 530.0]}], "attr": {"frame": 80}}, {"id": "SORXX/125830/SORKM_125830_2021Y11M25D_01H23M33S_img", "annotations": [{"id": 0, "type": "bbox", "attributes": {"occluded": false, "rotation": 0.0, "track_id": 0, "keyframe": true}, "group": 0, "label_id": 0, "z_order": 0, "bbox": [523.7, 1301.3, 464.4, 185.79999999999995]}, {"id": 0, "type": "bbox", "attributes": {"occluded": false, "rotation": 0.0, "track_id": 1, "keyframe": true}, "group": 0, "label_id": 0, "z_order": 0, "bbox": [590.69, 781.8, 39.309999999999945, 37.56000000000006]}, {"id": 0, "type": "bbox", "attributes": {"occluded": false, "rotation": 0.0, "track_id": 3, "keyframe": true}, "group": 0, "label_id": 0, "z_order": 0, "bbox": [1582.2, 682.1, 241.39999999999986, 135.79999999999995]}, {"id": 0, "type": "bbox", "attributes": {"occluded": false, "rotation": 0.0, "track_id": 2, "keyframe": true}, "group": 0, "label_id": 0, "z_order": 1, "bbox": [1592.0, 1038.9, 207.0999999999999, 525.8]}], "attr": {"frame": 81}}, {"id": "SORXX/125830/SORKM_125830_2021Y11M25D_12H03M22S_img", "annotations": [{"id": 0, "type": "bbox", "attributes": {"occluded": false, "rotation": 0.0, "track_id": 0, "keyframe": true}, "group": 0, "label_id": 0, "z_order": 0, "bbox": [523.7, 1274.3, 458.19999999999993, 208.70000000000005]}, {"id": 0, "type": "bbox", "attributes": {"occluded": false, "rotation": 0.0, "track_id": 1, "keyframe": true}, "group": 0, "label_id": 0, "z_order": 0, "bbox": [588.18, 781.1, 39.520000000000095, 38.92999999999995]}, {"id": 0, "type": "bbox", "attributes": {"occluded": false, "rotation": 0.0, "track_id": 3, "keyframe": true}, "group": 0, "label_id": 0, "z_order": 0, "bbox": [1579.7, 683.4, 243.0999999999999, 134.89999999999998]}, {"id": 0, "type": "bbox", "attributes": {"occluded": false, "rotation": 0.0, "track_id": 2, "keyframe": true}, "group": 0, "label_id": 0, "z_order": 1, "bbox": [1549.9, 1052.7, 249.19999999999982, 518.5999999999999]}], "attr": {"frame": 82}}, {"id": "SORXX/125830/SORKM_125830_2021Y11M25D_16H03M49S_img", "annotations": [{"id": 0, "type": "bbox", "attributes": {"occluded": false, "rotation": 0.0, "track_id": 0, "keyframe": true}, "group": 0, "label_id": 0, "z_order": 0, "bbox": [523.7, 1274.3, 458.19999999999993, 207.70000000000005]}, {"id": 0, "type": "bbox", "attributes": {"occluded": false, "rotation": 0.0, "track_id": 1, "keyframe": true}, "group": 0, "label_id": 0, "z_order": 0, "bbox": [588.51, 778.25, 41.01999999999998, 39.42999999999995]}, {"id": 0, "type": "bbox", "attributes": {"occluded": false, "rotation": 0.0, "track_id": 3, "keyframe": true}, "group": 0, "label_id": 0, "z_order": 0, "bbox": [1580.5, 679.2, 240.20000000000005, 134.5]}, {"id": 0, "type": "bbox", "attributes": {"occluded": false, "rotation": 0.0, "track_id": 2, "keyframe": true}, "group": 0, "label_id": 0, "z_order": 1, "bbox": [1543.9, 1052.7, 255.19999999999982, 516.2]}], "attr": {"frame": 83}}, {"id": "SORXX/125830/SORKM_125830_2021Y11M26D_00H26M28S_img", "annotations": [{"id": 0, "type": "bbox", "attributes": {"occluded": false, "rotation": 0.0, "track_id": 0, "keyframe": true}, "group": 0, "label_id": 0, "z_order": 0, "bbox": [516.4, 1274.3, 465.5, 207.70000000000005]}, {"id": 0, "type": "bbox", "attributes": {"occluded": false, "rotation": 0.0, "track_id": 1, "keyframe": true}, "group": 0, "label_id": 0, "z_order": 0, "bbox": [589.68, 780.8, 40.020000000000095, 40.40000000000009]}, {"id": 0, "type": "bbox", "attributes": {"occluded": false, "rotation": 0.0, "track_id": 3, "keyframe": true}, "group": 0, "label_id": 0, "z_order": 0, "bbox": [1576.4, 683.0, 243.0, 136.5]}, {"id": 0, "type": "bbox", "attributes": {"occluded": false, "rotation": 0.0, "track_id": 2, "keyframe": true}, "group": 0, "label_id": 0, "z_order": 1, "bbox": [1524.7, 1064.1, 274.39999999999986, 511.4000000000001]}], "attr": {"frame": 84}}, {"id": "SORXX/125830/SORKM_125830_2021Y11M26D_09H18M30S_img", "annotations": [{"id": 0, "type": "bbox", "attributes": {"occluded": false, "rotation": 0.0, "track_id": 0, "keyframe": true}, "group": 0, "label_id": 0, "z_order": 0, "bbox": [523.7, 1276.4, 465.5, 205.5999999999999]}, {"id": 0, "type": "bbox", "attributes": {"occluded": false, "rotation": 0.0, "track_id": 1, "keyframe": true}, "group": 0, "label_id": 0, "z_order": 0, "bbox": [589.68, 774.6, 40.520000000000095, 46.60000000000002]}, {"id": 0, "type": "bbox", "attributes": {"occluded": false, "rotation": 0.0, "track_id": 3, "keyframe": true}, "group": 0, "label_id": 0, "z_order": 0, "bbox": [1576.4, 683.0, 244.69999999999982, 134.39999999999998]}, {"id": 0, "type": "bbox", "attributes": {"occluded": false, "rotation": 0.0, "track_id": 2, "keyframe": true}, "group": 0, "label_id": 0, "z_order": 1, "bbox": [1510.9, 1071.3, 288.1999999999998, 504.20000000000005]}], "attr": {"frame": 85}}, {"id": "SORXX/125830/SORKM_125830_2021Y11M26D_13H17M33S_img", "annotations": [{"id": 0, "type": "bbox", "attributes": {"occluded": false, "rotation": 0.0, "track_id": 0, "keyframe": false}, "group": 0, "label_id": 0, "z_order": 0, "bbox": [526.8, 1280.55, 470.70000000000005, 201.45000000000005]}, {"id": 0, "type": "bbox", "attributes": {"occluded": false, "rotation": 0.0, "track_id": 1, "keyframe": true}, "group": 0, "label_id": 0, "z_order": 0, "bbox": [589.68, 770.1, 40.020000000000095, 51.10000000000002]}, {"id": 0, "type": "bbox", "attributes": {"occluded": false, "rotation": 0.0, "track_id": 3, "keyframe": true}, "group": 0, "label_id": 0, "z_order": 0, "bbox": [1574.7, 685.5, 241.79999999999995, 140.20000000000005]}, {"id": 0, "type": "bbox", "attributes": {"occluded": false, "rotation": 0.0, "track_id": 2, "keyframe": true}, "group": 0, "label_id": 0, "z_order": 1, "bbox": [1509.7, 1069.5, 289.39999999999986, 503.5999999999999]}], "attr": {"frame": 86}}, {"id": "SORXX/125830/SORKM_125830_2021Y11M27D_01H00M46S_img", "annotations": [{"id": 0, "type": "bbox", "attributes": {"occluded": false, "rotation": 0.0, "track_id": 0, "keyframe": true}, "group": 0, "label_id": 0, "z_order": 0, "bbox": [529.9, 1284.7, 475.9, 197.29999999999995]}, {"id": 0, "type": "bbox", "attributes": {"occluded": false, "rotation": 0.0, "track_id": 1, "keyframe": false}, "group": 0, "label_id": 0, "z_order": 0, "bbox": [589.68, 772.05, 40.92000000000007, 49.15000000000009]}, {"id": 0, "type": "bbox", "attributes": {"occluded": false, "rotation": 0.0, "track_id": 3, "keyframe": true}, "group": 0, "label_id": 0, "z_order": 0, "bbox": [1573.4, 690.5, 239.29999999999995, 169.79999999999995]}, {"id": 0, "type": "bbox", "attributes": {"occluded": false, "rotation": 0.0, "track_id": 2, "keyframe": true}, "group": 0, "label_id": 0, "z_order": 1, "bbox": [1474.9, 1082.7, 324.1999999999998, 497.0]}], "attr": {"frame": 87}}, {"id": "SORXX/125830/SORKM_125830_2021Y11M27D_12H45M31S_img", "annotations": [{"id": 0, "type": "bbox", "attributes": {"occluded": false, "rotation": 0.0, "track_id": 0, "keyframe": true}, "group": 0, "label_id": 0, "z_order": 0, "bbox": [529.9, 1224.5, 487.30000000000007, 257.5]}, {"id": 0, "type": "bbox", "attributes": {"occluded": false, "rotation": 0.0, "track_id": 1, "keyframe": true}, "group": 0, "label_id": 0, "z_order": 0, "bbox": [589.68, 774.0, 41.82000000000005, 47.200000000000045]}, {"id": 0, "type": "bbox", "attributes": {"occluded": false, "rotation": 0.0, "track_id": 3, "keyframe": true}, "group": 0, "label_id": 0, "z_order": 0, "bbox": [1573.0, 697.2, 245.0999999999999, 213.19999999999993]}, {"id": 0, "type": "bbox", "attributes": {"occluded": false, "rotation": 0.0, "track_id": 2, "keyframe": true}, "group": 0, "label_id": 0, "z_order": 1, "bbox": [1436.0, 1121.6, 363.0999999999999, 463.3000000000002]}], "attr": {"frame": 88}}, {"id": "SORXX/125830/SORKM_125830_2021Y11M28D_01H40M59S_img", "annotations": [{"id": 0, "type": "bbox", "attributes": {"occluded": false, "rotation": 0.0, "track_id": 0, "keyframe": true}, "group": 0, "label_id": 0, "z_order": 0, "bbox": [529.9, 1034.5, 504.9, 447.5]}, {"id": 0, "type": "bbox", "attributes": {"occluded": false, "rotation": 0.0, "track_id": 1, "keyframe": true}, "group": 0, "label_id": 0, "z_order": 0, "bbox": [589.68, 769.8, 39.42000000000007, 42.700000000000045]}, {"id": 0, "type": "bbox", "attributes": {"occluded": false, "rotation": 0.0, "track_id": 3, "keyframe": true}, "group": 0, "label_id": 0, "z_order": 0, "bbox": [1579.0, 700.8, 243.9000000000001, 277.5]}, {"id": 0, "type": "bbox", "attributes": {"occluded": false, "rotation": 0.0, "track_id": 2, "keyframe": true}, "group": 0, "label_id": 0, "z_order": 1, "bbox": [1397.1, 1151.9, 402.0, 437.29999999999995]}], "attr": {"frame": 89}}, {"id": "SORXX/125830/SORKM_125830_2021Y11M28D_12H19M51S_img", "annotations": [{"id": 0, "type": "bbox", "attributes": {"occluded": false, "rotation": 0.0, "track_id": 0, "keyframe": true}, "group": 0, "label_id": 0, "z_order": 0, "bbox": [529.9, 933.8, 505.9, 548.2]}, {"id": 0, "type": "bbox", "attributes": {"occluded": false, "rotation": 0.0, "track_id": 1, "keyframe": true}, "group": 0, "label_id": 0, "z_order": 0, "bbox": [589.68, 776.1, 37.32000000000005, 42.370000000000005]}, {"id": 0, "type": "bbox", "attributes": {"occluded": false, "rotation": 0.0, "track_id": 3, "keyframe": true}, "group": 0, "label_id": 0, "z_order": 0, "bbox": [1579.0, 715.2, 243.9000000000001, 325.5999999999999]}, {"id": 0, "type": "bbox", "attributes": {"occluded": false, "rotation": 0.0, "track_id": 2, "keyframe": true}, "group": 0, "label_id": 0, "z_order": 1, "bbox": [1376.3, 1178.7, 422.79999999999995, 419.20000000000005]}], "attr": {"frame": 90}}, {"id": "SORXX/125830/SORKM_125830_2021Y11M28D_16H19M48S_img", "annotations": [{"id": 0, "type": "bbox", "attributes": {"occluded": false, "rotation": 0.0, "track_id": 0, "keyframe": true}, "group": 0, "label_id": 0, "z_order": 0, "bbox": [529.9, 905.8, 511.1, 576.2]}, {"id": 0, "type": "bbox", "attributes": {"occluded": false, "rotation": 0.0, "track_id": 1, "keyframe": true}, "group": 0, "label_id": 0, "z_order": 0, "bbox": [589.68, 768.0, 37.620000000000005, 50.47000000000003]}, {"id": 0, "type": "bbox", "attributes": {"occluded": false, "rotation": 0.0, "track_id": 3, "keyframe": true}, "group": 0, "label_id": 0, "z_order": 0, "bbox": [1579.0, 705.6, 235.5, 338.19999999999993]}, {"id": 0, "type": "bbox", "attributes": {"occluded": false, "rotation": 0.0, "track_id": 2, "keyframe": true}, "group": 0, "label_id": 0, "z_order": 1, "bbox": [1376.3, 1167.5, 428.0, 424.29999999999995]}], "attr": {"frame": 91}}, {"id": "SORXX/125830/SORKM_125830_2021Y11M29D_00H39M03S_img", "annotations": [{"id": 0, "type": "bbox", "attributes": {"occluded": false, "rotation": 0.0, "track_id": 0, "keyframe": true}, "group": 0, "label_id": 0, "z_order": 0, "bbox": [529.9, 858.0, 530.8000000000001, 624.0]}, {"id": 0, "type": "bbox", "attributes": {"occluded": false, "rotation": 0.0, "track_id": 1, "keyframe": true}, "group": 0, "label_id": 0, "z_order": 0, "bbox": [587.6, 775.17, 37.00999999999999, 46.930000000000064]}, {"id": 0, "type": "bbox", "attributes": {"occluded": false, "rotation": 0.0, "track_id": 3, "keyframe": true}, "group": 0, "label_id": 0, "z_order": 0, "bbox": [1576.6, 718.8, 249.30000000000018, 366.5]}, {"id": 0, "type": "bbox", "attributes": {"occluded": false, "rotation": 0.0, "track_id": 2, "keyframe": true}, "group": 0, "label_id": 0, "z_order": 1, "bbox": [1380.6, 1176.2, 423.70000000000005, 420.79999999999995]}], "attr": {"frame": 92}}, {"id": "SORXX/125830/SORKM_125830_2021Y11M29D_13H22M14S_img", "annotations": [{"id": 0, "type": "bbox", "attributes": {"occluded": false, "rotation": 0.0, "track_id": 3, "keyframe": true}, "group": 0, "label_id": 0, "z_order": 0, "bbox": [1562.8, 720.6, 263.10000000000014, 425.9999999999999]}], "attr": {"frame": 93}}, {"id": "SORXX/125830/SORKM_125830_2021Y11M29D_17H21M48S_img", "annotations": [{"id": 0, "type": "bbox", "attributes": {"occluded": false, "rotation": 0.0, "track_id": 3, "keyframe": true}, "group": 0, "label_id": 0, "z_order": 0, "bbox": [1501.5, 691.8, 324.4000000000001, 426.0]}], "attr": {"frame": 94}}, {"id": "SORXX/125830/SORKM_125830_2021Y11M30D_01H19M40S_img", "annotations": [{"id": 0, "type": "bbox", "attributes": {"occluded": false, "rotation": 0.0, "track_id": 3, "keyframe": true}, "group": 0, "label_id": 0, "z_order": 0, "bbox": [1376.0, 630.4, 449.9000000000001, 390.5]}], "attr": {"frame": 95}}, {"id": "SORXX/125830/SORKM_125830_2021Y12M01D_17H28M27S_img", "annotations": [{"id": 0, "type": "bbox", "attributes": {"occluded": false, "rotation": 0.0, "track_id": 3, "keyframe": true}, "group": 0, "label_id": 0, "z_order": 0, "bbox": [1142.8, 520.1, 683.1000000000001, 266.1]}], "attr": {"frame": 96}}, {"id": "SORXX/125830/SORKM_125830_2021Y12M02D_00H16M00S_img", "annotations": [{"id": 0, "type": "bbox", "attributes": {"occluded": false, "rotation": 0.0, "track_id": 3, "keyframe": true}, "group": 0, "label_id": 0, "z_order": 0, "bbox": [1074.2, 416.3, 751.7, 336.7]}], "attr": {"frame": 97}}, {"id": "SORXX/125830/SORKM_125830_2021Y12M02D_12H24M20S_img", "annotations": [{"id": 0, "type": "bbox", "attributes": {"occluded": false, "rotation": 0.0, "track_id": 3, "keyframe": true}, "group": 0, "label_id": 0, "z_order": 0, "bbox": [1845.5, 541.5, 371.3000000000002, 514.5999999999999]}], "attr": {"frame": 98}}, {"id": "SORXX/125830/SORKM_125830_2021Y12M02D_16H24M24S_img", "annotations": [{"id": 0, "type": "bbox", "attributes": {"occluded": false, "rotation": 0.0, "track_id": 3, "keyframe": true}, "group": 0, "label_id": 0, "z_order": 0, "bbox": [1859.3, 450.67, 352.3100000000002, 339.83]}], "attr": {"frame": 99}}, {"id": "SORXX/125830/SORKM_125830_2021Y12M03D_00H57M50S_img", "annotations": [{"id": 0, "type": "bbox", "attributes": {"occluded": false, "rotation": 0.0, "track_id": 3, "keyframe": true}, "group": 0, "label_id": 0, "z_order": 0, "bbox": [1855.0, 411.7, 360.9000000000001, 343.3]}], "attr": {"frame": 100}}, {"id": "SORXX/125830/SORKM_125830_2021Y12M03D_09H35M49S_img", "annotations": [{"id": 0, "type": "bbox", "attributes": {"occluded": false, "rotation": 0.0, "track_id": 3, "keyframe": true}, "group": 0, "label_id": 0, "z_order": 0, "bbox": [1850.7, 412.6, 359.10000000000014, 329.4]}], "attr": {"frame": 101}}, {"id": "SORXX/125830/SORKM_125830_2021Y12M03D_13H33M51S_img", "annotations": [{"id": 0, "type": "bbox", "attributes": {"occluded": false, "rotation": 0.0, "track_id": 3, "keyframe": true}, "group": 0, "label_id": 0, "z_order": 0, "bbox": [1855.9, 424.7, 361.6999999999998, 310.40000000000003]}], "attr": {"frame": 102}}, {"id": "SORXX/125830/SORKM_125830_2021Y12M04D_01H32M30S_img", "annotations": [{"id": 0, "type": "bbox", "attributes": {"occluded": false, "rotation": 0.0, "track_id": 3, "keyframe": true}, "group": 0, "label_id": 0, "z_order": 0, "bbox": [1855.9, 464.5, 354.7999999999997, 396.0]}], "attr": {"frame": 103}}, {"id": "SORXX/125830/SORKM_125830_2021Y12M04D_13H00M08S_img", "annotations": [{"id": 0, "type": "bbox", "attributes": {"occluded": false, "rotation": 0.0, "track_id": 3, "keyframe": true}, "group": 0, "label_id": 0, "z_order": 0, "bbox": [1849.8, 532.0, 365.20000000000005, 451.29999999999995]}], "attr": {"frame": 104}}, {"id": "SORXX/125830/SORKM_125830_2021Y12M05D_00H29M06S_img", "annotations": [{"id": 0, "type": "bbox", "attributes": {"occluded": false, "rotation": 0.0, "track_id": 3, "keyframe": true}, "group": 0, "label_id": 0, "z_order": 0, "bbox": [1842.9, 539.8, 370.4000000000001, 499.70000000000005]}], "attr": {"frame": 105}}, {"id": "SORXX/125830/SORKM_125830_2021Y12M05D_12H28M38S_img", "annotations": [{"id": 0, "type": "bbox", "attributes": {"occluded": false, "rotation": 0.0, "track_id": 3, "keyframe": true}, "group": 0, "label_id": 0, "z_order": 0, "bbox": [1842.0, 563.2, 372.1999999999998, 510.0]}], "attr": {"frame": 106}}, {"id": "SORXX/125830/SORKM_125830_2021Y12M05D_16H28M38S_img", "annotations": [{"id": 0, "type": "bbox", "attributes": {"occluded": false, "rotation": 0.0, "track_id": 3, "keyframe": true}, "group": 0, "label_id": 0, "z_order": 0, "bbox": [1842.0, 568.4, 371.3000000000002, 517.8000000000001]}], "attr": {"frame": 107}}, {"id": "SORXX/125830/SORKM_125830_2021Y12M06D_01H10M09S_img", "annotations": [{"id": 0, "type": "bbox", "attributes": {"occluded": false, "rotation": 0.0, "track_id": 3, "keyframe": true}, "group": 0, "label_id": 0, "z_order": 0, "bbox": [1842.0, 610.8, 368.6999999999998, 510.0]}], "attr": {"frame": 108}}, {"id": "SORXX/125830/SORKM_125830_2021Y12M06D_13H38M22S_img", "annotations": [{"id": 0, "type": "bbox", "attributes": {"occluded": false, "rotation": 0.0, "track_id": 3, "keyframe": true}, "group": 0, "label_id": 0, "z_order": 0, "bbox": [1830.7, 627.2, 383.4999999999998, 466.79999999999995]}], "attr": {"frame": 109}}, {"id": "SORXX/125830/SORKM_125830_2021Y12M06D_17H39M01S_img", "annotations": [{"id": 0, "type": "bbox", "attributes": {"occluded": false, "rotation": 0.0, "track_id": 3, "keyframe": true}, "group": 0, "label_id": 0, "z_order": 0, "bbox": [1822.0, 624.6, 386.0999999999999, 484.9999999999999]}], "attr": {"frame": 110}}, {"id": "SORXX/125830/SORKM_125830_2021Y12M07D_00H02M32S_img", "annotations": [{"id": 0, "type": "bbox", "attributes": {"occluded": false, "rotation": 0.0, "track_id": 3, "keyframe": true}, "group": 0, "label_id": 0, "z_order": 0, "bbox": [1828.1, 648.0, 383.5, 479.79999999999995]}], "attr": {"frame": 111}}, {"id": "SORXX/125830/SORKM_125830_2021Y12M07D_09H05M42S_img", "annotations": [{"id": 0, "type": "bbox", "attributes": {"occluded": false, "rotation": 0.0, "track_id": 3, "keyframe": true}, "group": 0, "label_id": 0, "z_order": 0, "bbox": [1828.1, 648.0, 383.5, 483.29999999999995]}], "attr": {"frame": 112}}, {"id": "SORXX/125830/SORKM_125830_2021Y12M07D_13H04M45S_img", "annotations": [{"id": 0, "type": "bbox", "attributes": {"occluded": false, "rotation": 0.0, "track_id": 3, "keyframe": false}, "group": 0, "label_id": 0, "z_order": 0, "bbox": [1828.1, 648.0, 383.5, 489.79999999999995]}], "attr": {"frame": 113}}, {"id": "SORXX/125830/SORKM_125830_2021Y12M07D_17H05M29S_img", "annotations": [{"id": 0, "type": "bbox", "attributes": {"occluded": false, "rotation": 0.0, "track_id": 3, "keyframe": true}, "group": 0, "label_id": 0, "z_order": 0, "bbox": [1828.1, 648.0, 383.5, 496.29999999999995]}], "attr": {"frame": 114}}, {"id": "SORXX/125830/SORKM_125830_2021Y12M08D_00H48M16S_img", "annotations": [{"id": 0, "type": "bbox", "attributes": {"occluded": false, "rotation": 0.0, "track_id": 3, "keyframe": true}, "group": 0, "label_id": 0, "z_order": 0, "bbox": [1828.1, 655.8, 383.5, 491.10000000000014]}], "attr": {"frame": 115}}, {"id": "SORXX/125830/SORKM_125830_2021Y12M08D_08H40M50S_img", "annotations": [{"id": 0, "type": "bbox", "attributes": {"occluded": false, "rotation": 0.0, "track_id": 3, "keyframe": true}, "group": 0, "label_id": 0, "z_order": 0, "bbox": [1828.1, 655.8, 383.5, 492.79999999999995]}], "attr": {"frame": 116}}, {"id": "SORXX/125830/SORKM_125830_2021Y12M08D_12H40M17S_img", "annotations": [{"id": 0, "type": "bbox", "attributes": {"occluded": false, "rotation": 0.0, "track_id": 3, "keyframe": true}, "group": 0, "label_id": 0, "z_order": 0, "bbox": [1828.1, 642.8, 383.5, 499.70000000000005]}], "attr": {"frame": 117}}, {"id": "SORXX/125830/SORKM_125830_2021Y12M08D_16H40M29S_img", "annotations": [{"id": 0, "type": "bbox", "attributes": {"occluded": false, "rotation": 0.0, "track_id": 3, "keyframe": true}, "group": 0, "label_id": 0, "z_order": 0, "bbox": [1828.1, 637.6, 383.5, 514.4]}], "attr": {"frame": 118}}, {"id": "SORXX/125830/SORKM_125830_2021Y12M09D_01H22M09S_img", "annotations": [{"id": 0, "type": "bbox", "attributes": {"occluded": false, "rotation": 0.0, "track_id": 3, "keyframe": true}, "group": 0, "label_id": 0, "z_order": 0, "bbox": [1828.1, 605.6, 383.5, 534.3000000000001]}], "attr": {"frame": 119}}, {"id": "SORXX/125830/SORKM_125830_2021Y12M09D_12H02M57S_img", "annotations": [{"id": 0, "type": "bbox", "attributes": {"occluded": false, "rotation": 0.0, "track_id": 3, "keyframe": true}, "group": 0, "label_id": 0, "z_order": 0, "bbox": [1826.4, 535.5, 385.1999999999998, 540.4000000000001]}], "attr": {"frame": 120}}, {"id": "SORXX/125830/SORKM_125830_2021Y12M09D_16H02M57S_img", "annotations": [{"id": 0, "type": "bbox", "attributes": {"occluded": false, "rotation": 0.0, "track_id": 3, "keyframe": true}, "group": 0, "label_id": 0, "z_order": 0, "bbox": [1820.3, 494.0, 391.29999999999995, 581.9000000000001]}], "attr": {"frame": 121}}, {"id": "SORXX/125830/SORKM_125830_2021Y12M10D_00H25M48S_img", "annotations": [{"id": 0, "type": "bbox", "attributes": {"occluded": false, "rotation": 0.0, "track_id": 3, "keyframe": true}, "group": 0, "label_id": 0, "z_order": 0, "bbox": [1820.3, 437.8, 387.79999999999995, 664.9000000000001]}], "attr": {"frame": 122}}, {"id": "SORXX/125830/SORKM_125830_2021Y12M10D_09H18M04S_img", "annotations": [{"id": 0, "type": "bbox", "attributes": {"occluded": false, "rotation": 0.0, "track_id": 3, "keyframe": true}, "group": 0, "label_id": 0, "z_order": 0, "bbox": [1822.0, 355.6, 393.0, 756.6]}], "attr": {"frame": 123}}, {"id": "SORXX/125830/SORKM_125830_2021Y12M10D_13H17M09S_img", "annotations": [{"id": 0, "type": "bbox", "attributes": {"occluded": false, "rotation": 0.0, "track_id": 3, "keyframe": true}, "group": 0, "label_id": 0, "z_order": 0, "bbox": [1822.0, 283.8, 393.9000000000001, 825.8]}], "attr": {"frame": 124}}, {"id": "SORXX/125830/SORKM_125830_2021Y12M10D_16H52M54S_img", "annotations": [{"id": 0, "type": "bbox", "attributes": {"occluded": false, "rotation": 0.0, "track_id": 3, "keyframe": true}, "group": 0, "label_id": 0, "z_order": 0, "bbox": [1822.0, 275.1, 393.9000000000001, 850.6999999999999]}], "attr": {"frame": 125}}]}